{
  "biblioSummaryInfoArray": {
    "biblioSummaryInfo": {
      "applicationDate": "2016.02.12",
      "applicationFlag": "특허",
      "applicationNumber": "10-2016-0016588",
      "claimCount": "4",
      "examinerName": "윤동준",
      "finalDisposal": "등록결정(일반)",
      "inventionTitle": "약물 방출제어용 조성물",
      "inventionTitleEng": "Composition for Controlled Release of Drug",
      "openDate": "2016.03.02",
      "openNumber": "10-2016-0022848",
      "originalApplicationDate": "2013.12.09",
      "originalApplicationKind": "국내출원/분할",
      "originalApplicationNumber": "10-2013-0152683",
      "originalExaminationRequestDate": "2016.04.29",
      "originalExaminationRequestFlag": "Y",
      "publicationDate": "2017.11.16",
      "publicationNumber": "",
      "registerDate": "2017.11.09",
      "registerNumber": "10-1798184-0000",
      "registerStatus": "등록",
      "translationSubmitDate": ""
    }
  },
  "ipcInfoArray": {
    "ipcInfo": {
      "ipcDate": "(2006.01.01)",
      "ipcNumber": "A61K 9/20"
    }
  },
  "abstractInfoArray": {
    "abstractInfo": {
      "astrtCont": "본 발명은 약물 방출제어용 조성물에 관한 것이다. 구체적으로, 본 발명의 약물 방출제어용 조성물은 매트릭스 유형의 서방용 고분자가 기본 골격을 이루고, pH에 따라 졸-겔 변환이 일어나는 카보머로 상기 서방용 고분자의 방출제어능을 확충한다. 본 발명은 특히 방출 대상인 약물이 고난용성인 경우에 적합하도록 가용화제를, 그리고 충분한 초기 방출을 위해 붕해제를 추가로 함유함을 특징으로 한다. 본 발명의 약물 방출제어용 조성물은 서방용 고분자가 갖는 종래 매트릭스 구조의 서방성을 보유하면서, 졸-겔 변환성질을 가진 카보머를 도입하여 용출 후기 매트릭스 구조의 붕괴로 인한 약물의 급격한 방출을 예방할 수 있다. 아울러, 가용화제의 도입으로 인해 고난용성의 약물이 방출 이후에도 용해되지 않는 문제점을 해결하였으며, 붕해제를 도입하여 서방성 제제의 한계인 초기 방출속도를 향상시켰다."
    }
  },
  "claims": {
    "application_number": "1020160016588",
    "total_amendments": 4,
    "first_version": {
      "version": 1,
      "receipt_date": "20160212",
      "document_name": "[분할출원]특허출원서",
      "claim_count": 1,
      "claims": [
        {
          "claim_number": 1,
          "claim_type": "independent",
          "change_type": "신규",
          "change_code": "I",
          "text": "서방용 고분자 100 중량부, \n카보머(Carbomer) 5 내지 100 중량부, \n가용화제 10 내지 200 중량부, 및 \n붕해제 30 내지 70 중량부\n를 포함하는 약물 방출제어용 조성물.",
          "refers_to": []
        }
      ]
    },
    "last_version": {
      "version": 4,
      "receipt_date": "20170605",
      "document_name": "[명세서등 보정]보정서",
      "claim_count": 8,
      "claims": [
        {
          "claim_number": 1,
          "claim_type": "independent",
          "change_type": "수정",
          "change_code": "A",
          "text": "서방용 고분자로서 히드록시프로필메틸셀룰로오스(HPMC) 100 중량부, 카보머(Carbomer) 5 내지 100 중량부, 붕해제 30 내지 70 중량부,가용화제 10 내지 200 중량부, 및실로스타졸 10 내지 2000 중량부를 포함하는 약물 방출제어용 조성물로서, 상기 조성물은 비글견에 경구투여하였을 때 하기 약물동태학적 프로파일을 나타내는 약물 방출제어용 조성물:(a) Cmax/dose (ng/mL): 0.62±0.12, (b) Tmax(h): 4.17 ± 0.41, 및(c) T1/2(h): 8.34 ± 1.56.",
          "refers_to": []
        },
        {
          "claim_number": 2,
          "claim_type": "dependent",
          "change_type": "수정",
          "change_code": "A",
          "text": "제1항에 있어서,상기 가용화제는 소듐 라우릴 설페이트인 것인 약물 방출제어용 조성물.",
          "refers_to": [
            1
          ]
        },
        {
          "claim_number": 3,
          "claim_type": "dependent",
          "change_type": "수정",
          "change_code": "A",
          "text": "제1항에 있어서,상기 서방용 고분자는 50,000 내지 150,000 cps인 약물 방출제어용 조성물.",
          "refers_to": [
            1
          ]
        },
        {
          "claim_number": 4,
          "claim_type": "dependent",
          "change_type": "수정",
          "change_code": "A",
          "text": "제1항에 있어서, 상기 붕해제는 크로스카멜로스-소듐 (Crosscamellose-Na), 소듐 스타치 글리콜레이트 (Sodium starch glycolate), 프리젤라틴화 스타치 (Pregelatinized Starch), 미세결정 셀룰로오즈 (microcrystalline cellulose), 크로스포비돈 (Crospovidone, cross-linked povidone), 폴리비닐피롤리돈(Polyvinylpyrrolidone, PVP), 저치환 히드록시프로필셀룰로오스 (Hydroxypropylcellulose, low substituted), 알긴산 (alginic acid), 카르복시메틸셀룰로오즈 (Carboxymethylcellulose)의 칼슘염 또는 소듐염, 콜로이드성 이산화규소 (Fumed silica collidal silica), 구아검 (guar gum), 마그네슘 알루미늄 실리케이트 (Magnesium alumimum silicate), 메틸셀룰로오즈 (methylcellulose), 분말성 셀룰로오즈, 전분(starch), 소듐 알지네이트 (sodium alginate) 및 그 혼합물로 구성된 군에서 선택된 것인 약물 방출제어용 조성물.",
          "refers_to": [
            1
          ]
        },
        {
          "claim_number": 5,
          "claim_type": "independent",
          "change_type": "삭제",
          "change_code": "D",
          "text": "",
          "refers_to": []
        },
        {
          "claim_number": 6,
          "claim_type": "independent",
          "change_type": "삭제",
          "change_code": "D",
          "text": "",
          "refers_to": []
        },
        {
          "claim_number": 7,
          "claim_type": "independent",
          "change_type": "삭제",
          "change_code": "D",
          "text": "",
          "refers_to": []
        },
        {
          "claim_number": 8,
          "claim_type": "independent",
          "change_type": "삭제",
          "change_code": "D",
          "text": "",
          "refers_to": []
        }
      ]
    },
    "all_versions": [
      {
        "version": 1,
        "receipt_date": "20160212",
        "document_name": "[분할출원]특허출원서",
        "claim_count": 1,
        "claims": [
          {
            "claim_number": 1,
            "claim_type": "independent",
            "change_type": "신규",
            "change_code": "I",
            "text": "서방용 고분자 100 중량부, \n카보머(Carbomer) 5 내지 100 중량부, \n가용화제 10 내지 200 중량부, 및 \n붕해제 30 내지 70 중량부\n를 포함하는 약물 방출제어용 조성물.",
            "refers_to": []
          }
        ]
      },
      {
        "version": 2,
        "receipt_date": "20160429",
        "document_name": "[명세서등 보정]보정서",
        "claim_count": 8,
        "claims": [
          {
            "claim_number": 1,
            "claim_type": "independent",
            "change_type": "수정",
            "change_code": "A",
            "text": "서방용 고분자 100 중량부, \n카보머(Carbomer) 5 내지 100 중량부, \n부형제 및\n난용성 약물 10 내지 200 중량부\n를 포함하는 약물 방출제어용 조성물.",
            "refers_to": []
          },
          {
            "claim_number": 2,
            "claim_type": "dependent",
            "change_type": "신규",
            "change_code": "I",
            "text": "제1항에 있어서,\n상기 서방용 고분자는 히드록시프로필셀룰로오스(HPC), 히드록시프로필메틸셀룰로오스(HPMC), 폴리비닐알코올(PVA), 카보폴(Carbopol), 폴리에틸렌옥사이드(PEO) 및 그 공중합체나 혼합물로 이루어진 군에서 선택된 것인 약물 방출제어용 조성물.",
            "refers_to": [
              1
            ]
          },
          {
            "claim_number": 3,
            "claim_type": "dependent",
            "change_type": "신규",
            "change_code": "I",
            "text": "제1항에 있어서,\n상기 서방용 고분자는 50,000 내지 150,000 cps인 약물 방출제어용 조성물.",
            "refers_to": [
              1
            ]
          },
          {
            "claim_number": 4,
            "claim_type": "dependent",
            "change_type": "신규",
            "change_code": "I",
            "text": "제1항에 있어서, \n상기 부형제는 크로스카멜로스-소듐 (Crosscamellose-Na), 소듐 스타치 글리콜레이트 (Sodium starch glycolate), 프리젤라틴화 스타치 (Pregelatinized Starch), 미세결정 셀룰로오즈 (microcrystalline cellulose), 크로스포비돈 (Crospovidone, cross-linked povidone), 폴리비닐피롤리돈(Polyvinylpyrrolidone, PVP), 저치환 히드록시프로필셀룰로오스 (Hydroxypropylcellulose, low substituted), 알긴산 (alginic acid), 카르복시메틸셀룰로오즈 (Carboxymethylcellulose)의 칼슘염 또는 소듐염, 콜로이드성 이산화규소 (Fumed silica collidal silica), 구아검 (guar gum), 마그네슘 알루미늄 실리케이트 (Magnesium alumimum silicate), 메틸셀룰로오즈 (methylcellulose), 분말성 셀룰로오즈, 전분(starch), 소듐 알지네이트 (sodium alginate) 및 그 혼합물로 구성된 군에서 선택된 것인 약물 방출제어용 조성물.",
            "refers_to": [
              1
            ]
          },
          {
            "claim_number": 5,
            "claim_type": "dependent",
            "change_type": "신규",
            "change_code": "I",
            "text": "제1항에 있어서, \n상기 난용성 약물은 실로스타졸, 레바미피드, 아리피페라졸, 이르베사르탄, 아타자나비어 및 라부코나졸로 이루어진 군에서 선택된 것인 약물 방출제어용 조성물.",
            "refers_to": [
              1
            ]
          },
          {
            "claim_number": 6,
            "claim_type": "dependent",
            "change_type": "신규",
            "change_code": "I",
            "text": "제4항에 있어서, \n도 2에 도시된 용출 패턴을 갖는 약물 방출제어용 조성물.",
            "refers_to": [
              4
            ]
          },
          {
            "claim_number": 7,
            "claim_type": "dependent",
            "change_type": "신규",
            "change_code": "I",
            "text": "제4항에 있어서,\n도 3에 도시된 용출 패턴을 갖는 약물 방출제어용 조성물.",
            "refers_to": [
              4
            ]
          },
          {
            "claim_number": 8,
            "claim_type": "dependent",
            "change_type": "신규",
            "change_code": "I",
            "text": "제7항에 있어서,\n도 4에 도시된 실시예 2의 시간당 혈장레벨(ng/ml) 패턴 또는 도 5에 도시된 실시예 2의 시간당 혈장레벨(ng/ml) 패턴을 갖는 약물 방출제어용 조성물.",
            "refers_to": [
              7
            ]
          }
        ]
      },
      {
        "version": 3,
        "receipt_date": "20161018",
        "document_name": "[명세서등 보정]보정서",
        "claim_count": 7,
        "claims": [
          {
            "claim_number": 1,
            "claim_type": "independent",
            "change_type": "수정",
            "change_code": "A",
            "text": "서방용 고분자로서 히드록시프로필메틸셀룰로오스(HPMC) 100 중량부, \n카보머(Carbomer) 5 내지 100 중량부, \n붕해제 30 내지 70 중량부,\n가용화제 10 내지 200 중량부, 및\n실로스타졸, 레바미피드 및 아리피페라졸로 이루어진 군에서 선택된 난용성 약물 10 내지 2000 중량부\n를 포함하는 약물 방출제어용 조성물.",
            "refers_to": []
          },
          {
            "claim_number": 2,
            "claim_type": "dependent",
            "change_type": "수정",
            "change_code": "A",
            "text": "제1항에 있어서,\n상기 가용화제는 소듐 라우릴 설페이트인 것인 약물 방출제어용 조성물.",
            "refers_to": [
              1
            ]
          },
          {
            "claim_number": 4,
            "claim_type": "dependent",
            "change_type": "수정",
            "change_code": "A",
            "text": "제1항에 있어서, \n상기 붕해제는 크로스카멜로스-소듐 (Crosscamellose-Na), 소듐 스타치 글리콜레이트 (Sodium starch glycolate), 프리젤라틴화 스타치 (Pregelatinized Starch), 미세결정 셀룰로오즈 (microcrystalline cellulose), 크로스포비돈 (Crospovidone, cross-linked povidone), 폴리비닐피롤리돈(Polyvinylpyrrolidone, PVP), 저치환 히드록시프로필셀룰로오스 (Hydroxypropylcellulose, low substituted), 알긴산 (alginic acid), 카르복시메틸셀룰로오즈 (Carboxymethylcellulose)의 칼슘염 또는 소듐염, 콜로이드성 이산화규소 (Fumed silica collidal silica), 구아검 (guar gum), 마그네슘 알루미늄 실리케이트 (Magnesium alumimum silicate), 메틸셀룰로오즈 (methylcellulose), 분말성 셀룰로오즈, 전분(starch), 소듐 알지네이트 (sodium alginate) 및 그 혼합물로 구성된 군에서 선택된 것인 약물 방출제어용 조성물.",
            "refers_to": [
              1
            ]
          },
          {
            "claim_number": 5,
            "claim_type": "independent",
            "change_type": "삭제",
            "change_code": "D",
            "text": "",
            "refers_to": []
          },
          {
            "claim_number": 6,
            "claim_type": "independent",
            "change_type": "삭제",
            "change_code": "D",
            "text": "",
            "refers_to": []
          },
          {
            "claim_number": 7,
            "claim_type": "independent",
            "change_type": "삭제",
            "change_code": "D",
            "text": "",
            "refers_to": []
          },
          {
            "claim_number": 8,
            "claim_type": "independent",
            "change_type": "삭제",
            "change_code": "D",
            "text": "",
            "refers_to": []
          }
        ]
      },
      {
        "version": 4,
        "receipt_date": "20170605",
        "document_name": "[명세서등 보정]보정서",
        "claim_count": 1,
        "claims": [
          {
            "claim_number": 1,
            "claim_type": "independent",
            "change_type": "수정",
            "change_code": "A",
            "text": "서방용 고분자로서 히드록시프로필메틸셀룰로오스(HPMC) 100 중량부, \n카보머(Carbomer) 5 내지 100 중량부, \n붕해제 30 내지 70 중량부,\n가용화제 10 내지 200 중량부, 및\n실로스타졸 10 내지 2000 중량부\n를 포함하는 약물 방출제어용 조성물로서, 상기 조성물은 비글견에 경구투여하였을 때 하기 약물동태학적 프로파일을 나타내는 약물 방출제어용 조성물:\n(a) Cmax/dose (ng/mL): 0.62±0.12, \n(b) Tmax(h): 4.17 ± 0.41, 및\n(c) T1/2(h): 8.34 ± 1.56.",
            "refers_to": []
          }
        ]
      }
    ],
    "summary": {
      "before_claim_count": 1,
      "after_claim_count": 1,
      "total_versions": 4
    }
  },
  "familyInfoArray": {
    "familyInfo": {
      "familyApplicationNumber": "1020130152683"
    }
  },
  "internationalInfoArray": {
    "internationalInfo": {
      "internationOpenDate": "",
      "internationOpenNumber": "",
      "internationalApplicationDate": "",
      "internationalApplicationNumber": ""
    }
  },
  "applicantInfoArray": {
    "applicantInfo": {
      "address": "세종특별자치시  ...",
      "code": "119980048258",
      "country": "대한민국",
      "engName": "KOREA UNITED PHARM. INC.",
      "name": "한국유나이티드제약 주식회사"
    }
  },
  "inventorInfoArray": {
    "inventorInfo": [
      {
        "address": "경기도 안산시 단원구...",
        "code": "",
        "country": "대한민국",
        "engName": "CHOI, Yun Woong",
        "name": "최연웅"
      },
      {
        "address": "경기도 수원시 영통구...",
        "code": "",
        "country": "대한민국",
        "engName": "CHO, Sang Min",
        "name": "조상민"
      },
      {
        "address": "서울특별시 은평구...",
        "code": "",
        "country": "대한민국",
        "engName": "MIN, Byung Gu",
        "name": "민병구"
      },
      {
        "address": "경상남도 창원시 ...",
        "code": "",
        "country": "대한민국",
        "engName": "PARK, Jin Ha",
        "name": "박진하"
      },
      {
        "address": "서울특별시 관악구...",
        "code": "",
        "country": "대한민국",
        "engName": "KIM, Bo Kyung",
        "name": "김보경"
      }
    ]
  },
  "agentInfoArray": {
    "agentInfo": {
      "address": "서울특별시 송파구 법원로 ***, *층(문정동)(특허법인한얼)",
      "code": "919990004206",
      "country": "대한민국",
      "engName": "MIN SON",
      "name": "손민"
    }
  },
  "priorityInfoArray": "",
  "designatedStateInfoArray": "",
  "priorArtDocumentsInfoArray": {
    "priorArtDocumentsInfo": [
      {
        "documentsNumber": "KR1020100027337 A",
        "examinerQuotationFlag": "Y"
      },
      {
        "documentsNumber": "US07144585 B1",
        "examinerQuotationFlag": "Y"
      }
    ]
  },
  "legalStatusInfoArray": {
    "legalStatusInfo": [
      {
        "commonCodeName": "수리 (Accepted)",
        "documentEngName": "[Divisional Application] Patent Application",
        "documentName": "[분할출원]특허출원서",
        "receiptDate": "2016.02.12",
        "receiptNumber": "1-1-2016-0142856-07"
      },
      {
        "commonCodeName": "보정승인간주 (Regarded as an acceptance of amendment)",
        "documentEngName": "[Amendment to Description, etc.] Amendment",
        "documentName": "[명세서등 보정]보정서",
        "receiptDate": "2016.04.29",
        "receiptNumber": "1-1-2016-0416933-18"
      },
      {
        "commonCodeName": "수리 (Accepted)",
        "documentEngName": "[Request for Examination] Request for Examination (Request for Preferential Examination)",
        "documentName": "[심사청구]심사청구(우선심사신청)서",
        "receiptDate": "2016.04.29",
        "receiptNumber": "1-1-2016-0416946-12"
      },
      {
        "commonCodeName": "발송처리완료 (Completion of Transmission)",
        "documentEngName": "Notification of Return of Official Fee",
        "documentName": "수수료 반환 안내서",
        "receiptDate": "2016.05.11",
        "receiptNumber": "1-5-2016-0069647-18"
      },
      {
        "commonCodeName": "발송처리완료 (Completion of Transmission)",
        "documentEngName": "Notification of reason for refusal",
        "documentName": "의견제출통지서",
        "receiptDate": "2016.07.18",
        "receiptNumber": "9-5-2016-0516423-15"
      },
      {
        "commonCodeName": "수리 (Accepted)",
        "documentEngName": "[Designated Period Extension] Application of Period Extension(Reduction, Progress relief)",
        "documentName": "[지정기간연장]기간연장(단축, 경과구제)신청서",
        "receiptDate": "2016.09.19",
        "receiptNumber": "1-1-2016-0900971-18"
      },
      {
        "commonCodeName": "보정승인간주 (Regarded as an acceptance of amendment)",
        "documentEngName": "[Amendment to Description, etc.] Amendment",
        "documentName": "[명세서등 보정]보정서",
        "receiptDate": "2016.10.18",
        "receiptNumber": "1-1-2016-1008536-15"
      },
      {
        "commonCodeName": "수리 (Accepted)",
        "documentEngName": "[Opinion according to the Notification of Reasons for Refusal] Written Opinion(Written Reply, Written Substantiation)",
        "documentName": "[거절이유 등 통지에 따른 의견]의견(답변, 소명)서",
        "receiptDate": "2016.10.18",
        "receiptNumber": "1-1-2016-1008535-70"
      },
      {
        "commonCodeName": "수리 (Accepted)",
        "documentEngName": "Notification of change of applicant's information",
        "documentName": "출원인정보변경(경정)신고서",
        "receiptDate": "2016.11.14",
        "receiptNumber": "4-1-2016-5165131-84"
      },
      {
        "commonCodeName": "수리 (Accepted)",
        "documentEngName": "Notification of change of applicant's information",
        "documentName": "출원인정보변경(경정)신고서",
        "receiptDate": "2017.01.12",
        "receiptNumber": "4-1-2017-5006294-12"
      },
      {
        "commonCodeName": "수리 (Accepted)",
        "documentEngName": "Notification of change of applicant's information",
        "documentName": "출원인정보변경(경정)신고서",
        "receiptDate": "2017.01.12",
        "receiptNumber": "4-1-2017-5006298-94"
      },
      {
        "commonCodeName": "발송처리완료 (Completion of Transmission)",
        "documentEngName": "Notification of reason for final refusal",
        "documentName": "최후의견제출통지서",
        "receiptDate": "2017.02.03",
        "receiptNumber": "9-5-2017-0088047-12"
      },
      {
        "commonCodeName": "수리 (Accepted)",
        "documentEngName": "[Designated Period Extension] Application of Period Extension(Reduction, Progress relief)",
        "documentName": "[지정기간연장]기간연장(단축, 경과구제)신청서",
        "receiptDate": "2017.04.03",
        "receiptNumber": "1-1-2017-0325768-14"
      },
      {
        "commonCodeName": "수리 (Accepted)",
        "documentEngName": "[Designated Period Extension] Application of Period Extension(Reduction, Progress relief)",
        "documentName": "[지정기간연장]기간연장(단축, 경과구제)신청서",
        "receiptDate": "2017.05.04",
        "receiptNumber": "1-1-2017-0432356-94"
      },
      {
        "commonCodeName": "수리 (Accepted)",
        "documentEngName": "[Opinion according to the Notification of Reasons for Refusal] Written Opinion(Written Reply, Written Substantiation)",
        "documentName": "[거절이유 등 통지에 따른 의견]의견(답변, 소명)서",
        "receiptDate": "2017.06.05",
        "receiptNumber": "1-1-2017-0535063-59"
      },
      {
        "commonCodeName": "보정승인 (Acceptance of amendment)",
        "documentEngName": "[Amendment to Description, etc.] Amendment",
        "documentName": "[명세서등 보정]보정서",
        "receiptDate": "2017.06.05",
        "receiptNumber": "1-1-2017-0535064-05"
      },
      {
        "commonCodeName": "발송처리완료 (Completion of Transmission)",
        "documentEngName": "Decision to grant",
        "documentName": "등록결정서",
        "receiptDate": "2017.10.25",
        "receiptNumber": "9-5-2017-0739734-52"
      },
      {
        "commonCodeName": "수리 (Accepted)",
        "documentEngName": "Notification of change of applicant's information",
        "documentName": "출원인정보변경(경정)신고서",
        "receiptDate": "2019.03.14",
        "receiptNumber": "4-1-2019-5049775-82"
      },
      {
        "commonCodeName": "수리 (Accepted)",
        "documentEngName": "Notification of change of applicant's information",
        "documentName": "출원인정보변경(경정)신고서",
        "receiptDate": "2019.05.10",
        "receiptNumber": "4-1-2019-5092237-38"
      },
      {
        "commonCodeName": "수리 (Accepted)",
        "documentEngName": "Notification of change of applicant's information",
        "documentName": "출원인정보변경(경정)신고서",
        "receiptDate": "2019.07.25",
        "receiptNumber": "4-1-2019-5149490-98"
      },
      {
        "commonCodeName": "수리 (Accepted)",
        "documentEngName": "",
        "documentName": "특허고객번호 정보변경(경정)신고서·정정신고서",
        "receiptDate": "2022.02.07",
        "receiptNumber": "4-1-2022-5027556-78"
      }
    ]
  },
  "imagePathInfo": {
    "docName": "1020160016588.jpg",
    "largePath": "http://plus.kipris.or.kr/openapi/fileToss.jsp?arg=2ba38663aa11ff0f6ca91af6061a2e00b44070258fcf8f04d6ad6b817dababeacaff546fae787305926e3414389af82ddb704bafc693a678731d6d65da6876e283a50830f9fa982a",
    "path": "http://plus.kipris.or.kr/openapi/fileToss.jsp?arg=ed43a0609e94d6e22d01c5c32ba711cff58ea52334a4f74f12f723f70445a6201bfe0633058c64eba17a26ca8de8d3cf73a382ca816734f3bb62947868c7db588bb3fac91b0928b4"
  },
  "rndInfoArray": ""
}