{
  "biblioSummaryInfoArray": {
    "biblioSummaryInfo": {
      "applicationDate": "2014.08.27",
      "applicationFlag": "",
      "applicationNumber": "10-2016-7007410",
      "claimCount": "3",
      "examinerName": "윤소라",
      "finalDisposal": "등록결정(재심사후)",
      "inventionTitle": "혈소판 농축물로부터 유도될 수 있는 생물활성 조성물, 및 이를 제조하는 방법 및 사용 방법",
      "inventionTitleEng": "BIOACTIVE COMPOSITIONS DERIVABLE FROM PLATELET  CONCENTRATES, AND METHODS FOR PREPARING AND USING  SAME",
      "openDate": "2016.05.16",
      "openNumber": "10-2016-0054496",
      "originalApplicationDate": "",
      "originalApplicationKind": "국제출원/신규",
      "originalApplicationNumber": "",
      "originalExaminationRequestDate": "2019.08.26",
      "originalExaminationRequestFlag": "Y",
      "publicationDate": "2021.10.18",
      "publicationNumber": "",
      "registerDate": "2021.10.08",
      "registerNumber": "10-2313054-0000",
      "registerStatus": "등록",
      "translationSubmitDate": "2016.03.21"
    }
  },
  "ipcInfoArray": {
    "ipcInfo": [
      {
        "ipcDate": "(2015.01.01)",
        "ipcNumber": "A61K 35/19"
      },
      {
        "ipcDate": "(2015.01.01)",
        "ipcNumber": "A61K 35/16"
      },
      {
        "ipcDate": "(2006.01.01)",
        "ipcNumber": "A61K 38/36"
      },
      {
        "ipcDate": "(2006.01.01)",
        "ipcNumber": "A61K 38/18"
      },
      {
        "ipcDate": "(2006.01.01)",
        "ipcNumber": "A61K 38/19"
      },
      {
        "ipcDate": "(2006.01.01)",
        "ipcNumber": "A61K 38/20"
      },
      {
        "ipcDate": "(2006.01.01)",
        "ipcNumber": "A61K 38/21"
      },
      {
        "ipcDate": "(2006.01.01)",
        "ipcNumber": "C12N 5/00"
      }
    ]
  },
  "abstractInfoArray": {
    "abstractInfo": {
      "astrtCont": "본 개시내용은 혈소판 농축물로부터 유도된 생물활성 분획을 포함하는 조성물, 상기 생물활성 분획을 만드는 방법, 그리고 상기 생물활성 분획이 보강된 배양 배지를 제시한다. 바람직한 생물활성 분획은 원상태 성장 인자들은 유익한 양 및 비율로 유지되면서, 비교적 낮은 피브리노겐 농도를 갖는다."
    }
  },
  "claims": {
    "application_number": "1020167007410",
    "total_amendments": 4,
    "first_version": {
      "version": 1,
      "receipt_date": "20160321",
      "document_name": "[특허출원]특허법 제203조에 따른 서면",
      "claim_count": 72,
      "claims": [
        {
          "claim_number": 1,
          "claim_type": "independent",
          "change_type": "신규",
          "change_code": "I",
          "text": "인간 혈액-유도된 혈소판 농축물의 생물활성 분획을 포함하는 조성물로서,\n상기 혈소판 농축물은 인간 혈소판과 인간 혈장을 포함하며, 상기 생물활성 분획은 피브리노겐, 알부민, 글로불린, 및 적어도 하나의 TGF-β1, EGF, FGF-염기성, PDGF-AA, PDGF-BB, SDF-1α, 및 VEGF이 포함된 상기 혈소판 농축물의 원상태 성분을 포함하는, 조성물.",
          "refers_to": []
        },
        {
          "claim_number": 2,
          "claim_type": "dependent",
          "change_type": "신규",
          "change_code": "I",
          "text": "청구항 1에 있어서, 상기 피브리노겐은 20,000 ng/mL 미만의 수준으로 존재하는, 조성물.",
          "refers_to": [
            1
          ]
        },
        {
          "claim_number": 3,
          "claim_type": "independent",
          "change_type": "신규",
          "change_code": "I",
          "text": "청구항 1 또는 2에 있어서, 각각의 상기 TGF-β1, EGF, FGF-염기성, PDGF-AA, PDGF-BB, SDF-1α, 및 VEGF를 포함하는, 조성물.",
          "refers_to": []
        },
        {
          "claim_number": 4,
          "claim_type": "independent",
          "change_type": "신규",
          "change_code": "I",
          "text": "상기 항에 있어서, 본 조성물은 본질적으로 헤파린이 없는, 조성물.",
          "refers_to": []
        },
        {
          "claim_number": 5,
          "claim_type": "independent",
          "change_type": "신규",
          "change_code": "I",
          "text": "상기 항에 있어서, 상기 생물활성 분획은 상기 혈소판 농축물에 대하여 원상태인 IL-1b, IL-6, IL-8, IL-10, IL-13, IL-17, IFN-감마, 및 TNF-알파중 적어도 하나, 그리고 바람직하게는 이들 각각을 또한 포함하는, 조성물.",
          "refers_to": []
        },
        {
          "claim_number": 6,
          "claim_type": "independent",
          "change_type": "신규",
          "change_code": "I",
          "text": "상기 항에 있어서, 상기 생물활성 분획은 액체 생물활성 분획이며, 여기서 상기 조성물은 다음을 포함하는 조성물:\n약 0.5 내지 2.5 g/dL의 글로불린, 바람직하게는 약 1 내지 2 g/dL의 글로불린;\n약 2 내지 5 g/dL의 알부민, 바람직하게는 약 3 내지 4 g/dL의 알부민;\n약 100 내지 200 mmol/L의 나트륨, 바람직하게는 약 120 내지 약 160 mmol/L의 나트륨;\n약 50 내지 120 mg/dL의 트리글리세라이드, 바람직하게는 약 60 내지 110 mg/dL의 트리글리세라이드; 및/또는\n약 150 내지 300 mg/dL의 글루코오스, 바람직하게는 약 150 내지 250 mg/dL의 글루코오스.",
          "refers_to": []
        },
        {
          "claim_number": 7,
          "claim_type": "independent",
          "change_type": "신규",
          "change_code": "I",
          "text": "상기 항에 있어서, 세제 잔유물이 없는, 조성물.",
          "refers_to": []
        },
        {
          "claim_number": 8,
          "claim_type": "independent",
          "change_type": "신규",
          "change_code": "I",
          "text": "상기 항에 있어서, 상기 생물활성 분획은 액체 생물활성 분획이며, 여기서 상기 PDGF-BB 농도는 1000 pg/mL 미만인, 조성물.",
          "refers_to": []
        },
        {
          "claim_number": 9,
          "claim_type": "independent",
          "change_type": "신규",
          "change_code": "I",
          "text": "상기 항에 있어서, 상기 생물활성 분획은 액체 생물활성 분획이며, 여기서 상기 PDGF-AA 농도는 3000 pg/mL 미만인, 조성물.",
          "refers_to": []
        },
        {
          "claim_number": 10,
          "claim_type": "independent",
          "change_type": "신규",
          "change_code": "I",
          "text": "상기 항에 있어서, 상기 생물활성 분획은 액체 생물활성 분획이며, 여기서 상기 TGF-β1 농도는 적어도 5000 pg/mL인, 조성물.",
          "refers_to": []
        },
        {
          "claim_number": 11,
          "claim_type": "independent",
          "change_type": "신규",
          "change_code": "I",
          "text": "상기 항에 있어서, 상기 생물활성 분획은 액체 생물활성 분획이며, 여기서 상기 VEGF 농도는 300 pg/mL 미만인, 조성물.",
          "refers_to": []
        },
        {
          "claim_number": 12,
          "claim_type": "independent",
          "change_type": "신규",
          "change_code": "I",
          "text": "상기 항에 있어서, 상기 생물활성 분획은 액체 생물활성 분획이며, 여기서 상기 원상태 성분은 하기를 포함하는, 조성물:\n상기 액체 생물활성 분획의 20,000 ng/ml 미만 수준에서 피브리노겐;\n상기 액체 생물활성 분획의 적어도 2 mg/dL 수준에서 알부민;\n상기 액체 생물활성 분획의 적어도 1 g/dL 수준에서 글로불린;\n상기 액체 생물활성 분획의 적어도 5000 pg/mL 수준에서 TGF-β1;\n상기 액체 생물활성 분획의 적어도 20 pg/mL 수준에서 EGF;\n상기 액체 생물활성 분획의 적어도 5 pg/mL 수준에서 FGF-베타;\n상기 액체 생물활성 분획의 적어도 200 pg/mL 수준에서 PDGF-AA;\n상기 액체 생물활성 분획의 적어도 50 pg/mL 수준에서 PDGF-BB;\n상기 액체 생물활성 분획의 적어도 100 pg/mL 수준에서 SDF-1α; 및\n상기 액체 생물활성 분획의 적어도 10 pg/mL 수준에서 VEGF.",
          "refers_to": []
        },
        {
          "claim_number": 13,
          "claim_type": "independent",
          "change_type": "신규",
          "change_code": "I",
          "text": "상기 항에 있어서,\n상기 조성물은 260-340 mmol/kg 범위의 오스몰농도를 갖는, 조성물.",
          "refers_to": []
        },
        {
          "claim_number": 14,
          "claim_type": "independent",
          "change_type": "신규",
          "change_code": "I",
          "text": "상기 항에 있어서, \n상기 조성물은 6.8 내지 7.8 범위의 pH를 갖는, 조성물.",
          "refers_to": []
        },
        {
          "claim_number": 15,
          "claim_type": "independent",
          "change_type": "신규",
          "change_code": "I",
          "text": "상기 항에 있어서,\n본 조성물은 상기 혈소판 농축물에 대하여 원상태가 아닌 헤파린은 포함하지 않는, 조성물.",
          "refers_to": []
        },
        {
          "claim_number": 16,
          "claim_type": "independent",
          "change_type": "신규",
          "change_code": "I",
          "text": "청구항 1 내지 15중 임의의 하나에 따른 조성물을 포함하는 세포 배양 배지.",
          "refers_to": []
        },
        {
          "claim_number": 17,
          "claim_type": "dependent",
          "change_type": "신규",
          "change_code": "I",
          "text": "청구항 16에 있어서, 헤파린이 없는 세포 배양 배지.",
          "refers_to": [
            16
          ]
        },
        {
          "claim_number": 18,
          "claim_type": "independent",
          "change_type": "신규",
          "change_code": "I",
          "text": "생물활성 조성물을 제조하는 방법에서, 이 방법은\n응고 물질을 혈소판 용해물 조성물에 부가하여, 응고된 물질을 만들고;\n상기 응고된 물질 안의 액체로부터 응고된 고형물을 분리시키고; 및\n상기 액체는 심층 여과를 거치는 것을 포함하는, 방법.",
          "refers_to": []
        },
        {
          "claim_number": 19,
          "claim_type": "dependent",
          "change_type": "신규",
          "change_code": "I",
          "text": "청구항 18에 있어서, \n상기 심층 여과는 양성 표면 전하를 갖는 심층 여과 매질로 수행되는, 방법.",
          "refers_to": [
            18
          ]
        },
        {
          "claim_number": 20,
          "claim_type": "independent",
          "change_type": "신규",
          "change_code": "I",
          "text": "청구항 18 또는 19에 있어서, \n상기 응고 물질은 염화칼슘 염을 포함하는, 방법.",
          "refers_to": []
        },
        {
          "claim_number": 21,
          "claim_type": "independent",
          "change_type": "신규",
          "change_code": "I",
          "text": "청구항 18 내지 20중 임의의 한 항에 있어서, \n상기 액체는 멸균 여과를 거치는 것을 또한 포함하는, 방법.",
          "refers_to": []
        },
        {
          "claim_number": 22,
          "claim_type": "independent",
          "change_type": "신규",
          "change_code": "I",
          "text": "청구항 18 내지 21중 임의의 한 항에 있어서,\n상기 혈소판 용해물 조성물은 이 안에 혈소판을 용해시키기 위하여 혈소판 농축물 조성물을 냉동하고, 해동하는 것이 포함된 공정에 의해 제조되는, 방법.",
          "refers_to": []
        },
        {
          "claim_number": 23,
          "claim_type": "dependent",
          "change_type": "신규",
          "change_code": "I",
          "text": "청구항 22에 있어서, \n상기 혈소판 농축물 조성물은 혈소판 및 혈장이 포함된 성분채집된 인간 혈소판 조성물을 포함하는, 방법.",
          "refers_to": [
            22
          ]
        },
        {
          "claim_number": 24,
          "claim_type": "independent",
          "change_type": "신규",
          "change_code": "I",
          "text": "청구항 18 내지 23중 임의의 한 항에 있어서, \n멸균된 용기 안에 상기 생물활성 조성물을 패키징하는 것을 또한 포함하는, 방법.",
          "refers_to": []
        },
        {
          "claim_number": 25,
          "claim_type": "independent",
          "change_type": "신규",
          "change_code": "I",
          "text": "환자, 임의로 인간 환자를 치료하는 방법에서, \n청구항 1 내지 15중 임의의 한 항에 따른 상기 조성물이 포함된 치료적 물질을 투여하는 것을 포함하는, 방법.",
          "refers_to": []
        },
        {
          "claim_number": 26,
          "claim_type": "independent",
          "change_type": "신규",
          "change_code": "I",
          "text": "생물활성 조성물을 제조하는 방법에서, \n혈소판 및 혈장이 포함된 인간 혈액-유도된 농축물의 혈소판을 용해시켜, 용해된 혈소판 제조물을 만들고;\n상기 용해된 혈소판 제조물 안에 피브리노겐을 피브린으로 전환시킴으로써 용해된 혈소판 제조물로부터 겔 응고를 형성시키고;\n상기 겔 응고로부터 액체를 빼내기 위하여 상기 겔 응고를 압착시키고; 및\n상기 겔 응고 고형물로부터 상기 액체를 분리시키는 것을 포함하는, 방법.",
          "refers_to": []
        },
        {
          "claim_number": 27,
          "claim_type": "independent",
          "change_type": "신규",
          "change_code": "I",
          "text": "혈소판 용해물 조성물을 가공하는 방법에서, \n혈소판 및 혈장이 포함된 인간 혈액-유도된 농축물의 혈소판을 용해시켜, 용해된 혈소판 제조물을 만들고;\n용해된 혈소판 제조물 안에 피브리노겐을 피브린으로 전환시켜 형성된 겔 응고를 압착시켜, 상기 겔 응고로부터 액체를 뽑아내는 것을 포함하는, 방법.",
          "refers_to": []
        },
        {
          "claim_number": 28,
          "claim_type": "independent",
          "change_type": "신규",
          "change_code": "I",
          "text": "혈소판 용해물 조성물을 가공하는 방법에서, 이 방법은 \n상기 액체 생물활성 분획으로부터 현탁된 고형물을 제거하기 위하여, 피브리노겐, 알부민, 글로불린, TGF-β1, EGF, FGF-베타, PDGF-AA, PDGF-BB, SDF-1α, 및 VEGF가 포함된 상기 혈소판 농축물의 원상태 성분을 포함하는 액체 인간 혈액-유도된 혈소판 농축물의 생물활성 분획을 적어도 제1 심층 필터를 통하여 통과시키는 것을 포함하고, 여기서 상기 피브리노겐은 20,000 ng/mL 미만 수준으로 존재하는, 방법.",
          "refers_to": []
        },
        {
          "claim_number": 29,
          "claim_type": "dependent",
          "change_type": "신규",
          "change_code": "I",
          "text": "청구항 28에 있어서, 상기 농축물의 액체 생물활성 분획으로부터 농축물의 응고된 분획을 분리시키기 위하여 원심분리 단계없이, 혈액-유도된 혈소판 농축물로부터 상기 액체 생물활성 분획을 획득하는 것을 더 포함하는, 방법.",
          "refers_to": [
            28
          ]
        },
        {
          "claim_number": 30,
          "claim_type": "dependent",
          "change_type": "신규",
          "change_code": "I",
          "text": "청구항 28에 있어서, 상기 획득은\n상기 농축물의 혈소판을 용해시켜 용해된 제조물을 만들고;\n상기 용해된 제조물의 피브리노겐을 피브린으로 전환시켜, 겔 응고를 만들고; 그리고\n원심분리 없이 상기 겔 응고를 압착시켜, 겔 응고로부터 상기 액체 생물활성 분획을 빼내는 것을 포함하는, 방법.",
          "refers_to": [
            28
          ]
        },
        {
          "claim_number": 31,
          "claim_type": "dependent",
          "change_type": "신규",
          "change_code": "I",
          "text": "청구항 30에 있어서, 상기 압착은 제1 표면과 제2 표면 사이에 접촉된 상기 겔 응고를 압착시켜, 상기 겔 응고로부터 상기 액체 생물활성 분획은 빼내고, 고형 응고 덩어리는 남아있게 하는 것을 포함하는, 방법.",
          "refers_to": [
            30
          ]
        },
        {
          "claim_number": 32,
          "claim_type": "independent",
          "change_type": "신규",
          "change_code": "I",
          "text": "청구항 28-31중 임의의 한 항에 있어서, 상기 통과에 의해 \nTGF-베타-1, EGF, FGF-b, PDGF-AA, PDGF-BB, SDF-1α, 및 VEGF 중 하나, 일부 또는 모두의 수준이 적어도 20% 감소; 및/또는\nTGF-베타-1의 수준이 적어도 50% 감소; 및/또는\nEGF의 수준이 적어도 30% 감소; 및/또는\nFGF-b의 수준이 적어도 20% 감소; 및/또는\nPDGF-AA의 수준이 적어도 50% 감소; 및/또는\nPDGF-BB의 수준이 적어도 50% 감소; 및/또는\nSDF-1α의 수준이 적어도 20% 감소; 및/또는\nVEGF의 수준이 적어도 30% 감소를 초래하는, 방법.",
          "refers_to": []
        },
        {
          "claim_number": 33,
          "claim_type": "independent",
          "change_type": "신규",
          "change_code": "I",
          "text": "세포를 동결보존하는 방법에서, \n청구항 1-15중 임의의 한 항에 따른 조성물이 포함된 세포 조성물을 냉동보존 조건에 두는 것을 포함하는, 방법.",
          "refers_to": []
        },
        {
          "claim_number": 34,
          "claim_type": "independent",
          "change_type": "신규",
          "change_code": "I",
          "text": "청구항 1-16중 임의의 한 항에 있어서, 상기 조성물은 액체 전달 장치 안에 보관된, 조성물.",
          "refers_to": []
        },
        {
          "claim_number": 35,
          "claim_type": "dependent",
          "change_type": "신규",
          "change_code": "I",
          "text": "청구항 34에 있어서, 상기 액체 전달 장치는 점안기를 포함하는, 조성물.",
          "refers_to": [
            34
          ]
        },
        {
          "claim_number": 36,
          "claim_type": "independent",
          "change_type": "신규",
          "change_code": "I",
          "text": "청구항 1-16중 임의의 한 항에 있어서 여기서 상기 조성물은 갯과 환자에서 질환 또는 병든 상태를 치료하는데 효과적인, 조성물.",
          "refers_to": []
        },
        {
          "claim_number": 37,
          "claim_type": "dependent",
          "change_type": "신규",
          "change_code": "I",
          "text": "청구항 36에 있어서, 상기 병든 상태는 건성각결막염을 포함하는, 조성물.",
          "refers_to": [
            36
          ]
        },
        {
          "claim_number": 38,
          "claim_type": "dependent",
          "change_type": "신규",
          "change_code": "I",
          "text": "청구항 1에 있어서, 상기 생물활성 분획은 액체 생물활성 분획이며, 그리고 여기서 본 조성물은 하기를 포함하는 조성물:\n약 200 pg/mL 내지 약 350 pg/mL 수준에서 FGF-2;\n약 1800 pg/mL 내지 약 3100 pg/mL 수준에서 EGF; \n약 24,000 pg/mL 내지 약 28,000 pg/mL 수준에서 PDGF-AA; \n약 50 ng/mL 내지 약 80 ng/mL 수준에서 PDGF-BB; \n약 500 pg/mL 내지 약 800 pg/mL 수준에서 VEGF; \n약 60 ng/mL 내지 약 90 ng/mL 수준에서 TGF-b; 그리고\n미만 2.5㎍/mL 미만의 수준에서 피브리노겐.",
          "refers_to": [
            1
          ]
        },
        {
          "claim_number": 39,
          "claim_type": "dependent",
          "change_type": "신규",
          "change_code": "I",
          "text": "청구항 1에 있어서, 상기 피브리노겐은 20,000 ng/mL 미만 수준으로 존재하는, 조성물.",
          "refers_to": [
            1
          ]
        },
        {
          "claim_number": 40,
          "claim_type": "dependent",
          "change_type": "신규",
          "change_code": "I",
          "text": "청구항 1에 있어서, 각각의 상기 TGF-β1, EGF, FGF-염기성, PDGF-AA, PDGF-BB, SDF-1α, 및 VEGF를 포함하는, 조성물.",
          "refers_to": [
            1
          ]
        },
        {
          "claim_number": 41,
          "claim_type": "dependent",
          "change_type": "신규",
          "change_code": "I",
          "text": "청구항 1에 있어서, 상기 조성물은 본질적으로 헤파린이 없는, 조성물.",
          "refers_to": [
            1
          ]
        },
        {
          "claim_number": 42,
          "claim_type": "dependent",
          "change_type": "신규",
          "change_code": "I",
          "text": "청구항 1에 있어서, 상기 생물활성 분획은 상기 혈소판 농축물에 원상태인 IL-1b, IL-6, IL-8, IL-10, IL-13, IL-17, IFN-감마, 및 TNF-알파중 적어도 하나, 그리고 바람직하게는 이들 각각을 또한 포함하는, 조성물.",
          "refers_to": [
            1
          ]
        },
        {
          "claim_number": 43,
          "claim_type": "dependent",
          "change_type": "신규",
          "change_code": "I",
          "text": "청구항 1에 있어서, 상기 생물활성 분획은 액체 생물활성 분획이며, 그리고 여기서 상기 조성물은 다음을 포함하는 조성물:\n약 0.5 내지 2.5 g/dL의 글로불린, 바람직하게는 약 1 내지 2 g/dL의 글로불린;\n약 2 내지 5 g/dL의 알부민, 바람직하게는 약 3 내지 4 g/dL의 알부민;\n약 100 내지 200 mmol/L의 나트륨, 바람직하게는 약 120 내지 약 160 mmol/L의 나트륨;\n약 50 내지 120 mg/dL의 트리글리세라이드, 바람직하게는 약 60 내지 110 mg/dL의 트리글리세라이드; 및/또는\n약 150 내지 300 mg/dL의 글루코오스, 바람직하게는 약 150 내지 250 mg/dL의 글루코오스.",
          "refers_to": [
            1
          ]
        },
        {
          "claim_number": 44,
          "claim_type": "dependent",
          "change_type": "신규",
          "change_code": "I",
          "text": "청구항 1에 있어서, 세제 잔유물이 없는, 조성물.",
          "refers_to": [
            1
          ]
        },
        {
          "claim_number": 45,
          "claim_type": "dependent",
          "change_type": "신규",
          "change_code": "I",
          "text": "청구항 1에 있어서, 상기 생물활성 분획은 액체 생물활성 분획이며, 그리고 여기서 상기 PDGF-BB 농도는 1000 pg/mL 미만인, 조성물.",
          "refers_to": [
            1
          ]
        },
        {
          "claim_number": 46,
          "claim_type": "dependent",
          "change_type": "신규",
          "change_code": "I",
          "text": "청구항 1에 있어서, 상기 생물활성 분획은 액체 생물활성 분획이며, 그리고 여기서 상기 PDGF-AA 농도는 3000 pg/mL 미만인, 조성물.",
          "refers_to": [
            1
          ]
        },
        {
          "claim_number": 47,
          "claim_type": "dependent",
          "change_type": "신규",
          "change_code": "I",
          "text": "청구항 1에 있어서, 상기 생물활성 분획은 액체 생물활성 분획이며, 그리고 여기서 상기 TGF-β1 농도는 적어도 5000 pg/mL인, 조성물.",
          "refers_to": [
            1
          ]
        },
        {
          "claim_number": 48,
          "claim_type": "dependent",
          "change_type": "신규",
          "change_code": "I",
          "text": "청구항 1에 있어서, 상기 생물활성 분획은 액체 생물활성 분획이며, 그리고 여기서 상기 VEGF 농도는 300 pg/mL 미만인, 조성물.",
          "refers_to": [
            1
          ]
        },
        {
          "claim_number": 49,
          "claim_type": "dependent",
          "change_type": "신규",
          "change_code": "I",
          "text": "청구항 1에 있어서, 상기 생물활성 분획은 액체 생물활성 분획이며, 그리고 여기서 상기 원상태 성분은 하기를 포함하는, 조성물:\n상기 액체 생물활성 분획의 20,000 ng/ml 미만 수준에서 피브리노겐;\n상기 액체 생물활성 분획의 적어도 2 mg/dL 수준에서 알부민;\n상기 액체 생물활성 분획의 적어도 1 g/dL 수준에서 글로불린;\n상기 액체 생물활성 분획의 적어도 5000 pg/mL 수준에서 TGF-β1 ;\n상기 액체 생물활성 분획의 적어도 20 pg/mL 수준에서 EGF;\n상기 액체 생물활성 분획의 적어도 5 pg/mL 수준에서 FGF-베타;\n상기 액체 생물활성 분획의 적어도 200 pg/mL 수준에서 PDGF-AA;\n상기 액체 생물활성 분획의 적어도 50 pg/mL 수준에서 PDGF-BB;\n상기 액체 생물활성 분획의 적어도 100 pg/mL 수준에서 SDF-1α; 그리고\n상기 액체 생물활성 분획의 적어도 10 pg/mL 수준에서 VEGF.",
          "refers_to": [
            1
          ]
        },
        {
          "claim_number": 50,
          "claim_type": "dependent",
          "change_type": "신규",
          "change_code": "I",
          "text": "청구항 1에 있어서, \n상기 조성물은 260-340 mmol/kg 범위의 오스몰농도를 갖는, 조성물",
          "refers_to": [
            1
          ]
        },
        {
          "claim_number": 51,
          "claim_type": "dependent",
          "change_type": "신규",
          "change_code": "I",
          "text": "청구항 1에 있어서, \n상기 조성물은 6.8 내지 7.8 범위의 pH를 갖는, 조성물.",
          "refers_to": [
            1
          ]
        },
        {
          "claim_number": 52,
          "claim_type": "dependent",
          "change_type": "신규",
          "change_code": "I",
          "text": "청구항 1에 있어서, \n본 조성물은 상기 혈소판 농축물에 대하여 원상태가 아닌 헤파린은 포함하지 않는, 조성물.",
          "refers_to": [
            1
          ]
        },
        {
          "claim_number": 53,
          "claim_type": "dependent",
          "change_type": "신규",
          "change_code": "I",
          "text": "청구항 1 에 따른 조성물을 포함하는 세포 배양 배지.",
          "refers_to": [
            1
          ]
        },
        {
          "claim_number": 54,
          "claim_type": "dependent",
          "change_type": "신규",
          "change_code": "I",
          "text": "청구항 51에 있어서, 헤파린이 없는 세포 배양 배지.",
          "refers_to": [
            51
          ]
        },
        {
          "claim_number": 55,
          "claim_type": "dependent",
          "change_type": "신규",
          "change_code": "I",
          "text": "청구항 18에 있어서, \n상기 심층 여과는 양성 표면 전하를 갖는 심층 여과 매질로 수행되는, 방법.",
          "refers_to": [
            18
          ]
        },
        {
          "claim_number": 56,
          "claim_type": "dependent",
          "change_type": "신규",
          "change_code": "I",
          "text": "청구항 18에 있어서, \n상기 응고 물질은 염화칼슘 염을 포함하는, 방법.",
          "refers_to": [
            18
          ]
        },
        {
          "claim_number": 57,
          "claim_type": "dependent",
          "change_type": "신규",
          "change_code": "I",
          "text": "청구항 18에 있어서, \n상기 액체는 멸균 여과를 거치는 것을 또한 포함하는, 방법.",
          "refers_to": [
            18
          ]
        },
        {
          "claim_number": 58,
          "claim_type": "dependent",
          "change_type": "신규",
          "change_code": "I",
          "text": "청구항 18에 있어서,\n상기 혈소판 용해물 조성물은 이 안에 혈소판을 용해시키기 위하여 혈소판 농축물 조성물을 냉동하고, 해동하는 것이 포함된 공정에 의해 제조되는, 방법.",
          "refers_to": [
            18
          ]
        },
        {
          "claim_number": 59,
          "claim_type": "dependent",
          "change_type": "신규",
          "change_code": "I",
          "text": "청구항 58에 있어서, \n상기 혈소판 농축물 조성물은 혈소판 및 혈장이 포함된 성분채집된 인간 혈소판 조성물을 포함하는, 방법.",
          "refers_to": [
            58
          ]
        },
        {
          "claim_number": 60,
          "claim_type": "dependent",
          "change_type": "신규",
          "change_code": "I",
          "text": "청구항 18에 있어서, \n멸균된 용기 안에 상기 생물활성 조성물을 패키징하는 것을 또한 포함하는, 방법.",
          "refers_to": [
            18
          ]
        },
        {
          "claim_number": 61,
          "claim_type": "dependent",
          "change_type": "신규",
          "change_code": "I",
          "text": "환자, 임의로 인간 환자를 치료하는 방법에서, \n청구항 1 에 따른 상기 조성물이 포함된 치료적 물질을 투여하는 것을 포함하는, 방법.",
          "refers_to": [
            1
          ]
        },
        {
          "claim_number": 62,
          "claim_type": "dependent",
          "change_type": "신규",
          "change_code": "I",
          "text": "청구항 28에 있어서, \n여기서 상기 통과에 의해 \nTGF-베타-1, EGF, FGF-b, PDGF-AA, PDGF-BB, SDF-1α, 및 VEGF 중 하나, 일부 또는 모두의 수준이 적어도 20% 감소; 및/또는\nTGF-베타-1의 수준이 적어도 50% 감소; 및/또는\nEGF의 수준이 적어도 30% 감소; 및/또는\nFGF-b의 수준이 적어도 20% 감소; 및/또는\nPDGF-AA의 수준이 적어도 50% 감소; 및/또는\nPDGF-BB의 수준이 적어도 50% 감소; 및/또는\nSDF-1α의 수준이 적어도 20% 감소; 및/또는\nVEGF의 수준이 적어도 30% 감소를 초래하는, 방법.",
          "refers_to": [
            28
          ]
        },
        {
          "claim_number": 63,
          "claim_type": "dependent",
          "change_type": "신규",
          "change_code": "I",
          "text": "세포를 동결보존하는 방법에서, \n청구항 1에 따른 조성물이 포함된 세포 조성물을 냉동보존 조건에 두는 것을 포함하는, 방법.",
          "refers_to": [
            1
          ]
        },
        {
          "claim_number": 64,
          "claim_type": "dependent",
          "change_type": "신규",
          "change_code": "I",
          "text": "청구항 1에 있어서, 상기 조성물은 액체 전달 장치 안에 보관된, 조성물.",
          "refers_to": [
            1
          ]
        },
        {
          "claim_number": 65,
          "claim_type": "dependent",
          "change_type": "신규",
          "change_code": "I",
          "text": "청구항 64에 있어서, 상기 액체 전달 장치는 점안기를 포함하는, 조성물.",
          "refers_to": [
            64
          ]
        },
        {
          "claim_number": 66,
          "claim_type": "dependent",
          "change_type": "신규",
          "change_code": "I",
          "text": "청구항 1에 있어서, 상기 조성물은 갯과 환자에서 질환 또는 병든 상태를 치료하는데 효과적인, 조성물.",
          "refers_to": [
            1
          ]
        },
        {
          "claim_number": 67,
          "claim_type": "dependent",
          "change_type": "신규",
          "change_code": "I",
          "text": "청구항 66에 있어서, 상기 병든 상태는 건성각결막염을 포함하는, 조성물.",
          "refers_to": [
            66
          ]
        },
        {
          "claim_number": 68,
          "claim_type": "independent",
          "change_type": "신규",
          "change_code": "I",
          "text": "생물활성 조성물을 제조하는 방법에서, \n응고 물질을 혈소판 용해물 조성물에 부가하여 응고된 물질을 만들고;\n상기 응고된 물질로부터 응고된 고형물을 분리시키고; 그리고\n상기 액체는 여과를 거치는 것을 포함하는, 방법.",
          "refers_to": []
        },
        {
          "claim_number": 69,
          "claim_type": "dependent",
          "change_type": "신규",
          "change_code": "I",
          "text": "청구항 68에 있어서, \n상기 응고 물질은 염화칼슘 염을 포함하는, 방법.",
          "refers_to": [
            68
          ]
        },
        {
          "claim_number": 70,
          "claim_type": "dependent",
          "change_type": "신규",
          "change_code": "I",
          "text": "청구항 68에 있어서, \n상기 혈소판 용해물 조성물은 이 안에 혈소판을 용해시키기 위하여 혈소판 농축물 조성물을 냉동하고, 해동하는 것이 포함된 공정에 의해 제조되는, 방법.",
          "refers_to": [
            68
          ]
        },
        {
          "claim_number": 71,
          "claim_type": "dependent",
          "change_type": "신규",
          "change_code": "I",
          "text": "청구항 68에 있어서, \n상기 혈소판 농축물 조성물은 혈소판 및 혈장이 포함된 성분채집된 인간 혈소판 조성물을 포함하는, 방법.",
          "refers_to": [
            68
          ]
        },
        {
          "claim_number": 72,
          "claim_type": "dependent",
          "change_type": "신규",
          "change_code": "I",
          "text": "청구항 68에 있어서, \n멸균된 용기 안에 상기 생물활성 조성물을 패키징하는 것을 또한 포함하는, 방법.",
          "refers_to": [
            68
          ]
        }
      ]
    },
    "last_version": {
      "version": 4,
      "receipt_date": "20210625",
      "document_name": "[명세서등 보정]보정서(재심사)",
      "claim_count": 72,
      "claims": [
        {
          "claim_number": 1,
          "claim_type": "independent",
          "change_type": "수정",
          "change_code": "A",
          "text": "생물활성(bioactive) 조성물의 제조 방법으로서, 상기 방법이:혈소판 및 혈장을 포함하는 인간 혈액-유래된 농축물의 혈소판을 용해시켜 용해된 혈소판 제제(preparation)를 형성하는 단계;상기 용해된 혈소판 제제에서 피브리노겐을 피브린으로 전환시키는 응고제를 첨가하여 상기 용해된 혈소판 제제로부터 응고 겔(gel clot)을 형성하는 단계;상기 응고 겔을 압축(compress)하여 응고 겔로부터 액체를 짜내고(express) 상기 응고 겔의 고체로부터 액체를 분리하는 단계를 포함하고, 상기 압축 단계는 2개 이상의 표면 사이에서 응고 겔을 압박(press)하는 단계를 포함하고;상기 생물활성 조성물의 제조 동안 헤파린이 첨가되지 않고;상기 생물활성 조성물이 20,000 ng/mL 미만의 수준으로 피브리노겐을 포함하는, 생물활성 조성물의 제조 방법.",
          "refers_to": []
        },
        {
          "claim_number": 2,
          "claim_type": "dependent",
          "change_type": "수정",
          "change_code": "A",
          "text": "청구항 1에 있어서, 상기 생물활성 조성물을 세포성 현탁 조성물 안에 혼입시키는 단계를 추가로 포함하는, 방법,",
          "refers_to": [
            1
          ]
        },
        {
          "claim_number": 3,
          "claim_type": "dependent",
          "change_type": "수정",
          "change_code": "A",
          "text": "청구항 2에 있어서, 상기 세포성 현탁 조성물을 냉동보존시키는 단계를 추가로 포함하는, 방법.",
          "refers_to": [
            2
          ]
        },
        {
          "claim_number": 4,
          "claim_type": "independent",
          "change_type": "삭제",
          "change_code": "D",
          "text": "",
          "refers_to": []
        },
        {
          "claim_number": 5,
          "claim_type": "independent",
          "change_type": "삭제",
          "change_code": "D",
          "text": "",
          "refers_to": []
        },
        {
          "claim_number": 6,
          "claim_type": "independent",
          "change_type": "삭제",
          "change_code": "D",
          "text": "",
          "refers_to": []
        },
        {
          "claim_number": 7,
          "claim_type": "independent",
          "change_type": "삭제",
          "change_code": "D",
          "text": "",
          "refers_to": []
        },
        {
          "claim_number": 8,
          "claim_type": "independent",
          "change_type": "삭제",
          "change_code": "D",
          "text": "",
          "refers_to": []
        },
        {
          "claim_number": 9,
          "claim_type": "independent",
          "change_type": "삭제",
          "change_code": "D",
          "text": "",
          "refers_to": []
        },
        {
          "claim_number": 10,
          "claim_type": "independent",
          "change_type": "삭제",
          "change_code": "D",
          "text": "",
          "refers_to": []
        },
        {
          "claim_number": 11,
          "claim_type": "independent",
          "change_type": "삭제",
          "change_code": "D",
          "text": "",
          "refers_to": []
        },
        {
          "claim_number": 12,
          "claim_type": "independent",
          "change_type": "삭제",
          "change_code": "D",
          "text": "",
          "refers_to": []
        },
        {
          "claim_number": 13,
          "claim_type": "independent",
          "change_type": "삭제",
          "change_code": "D",
          "text": "",
          "refers_to": []
        },
        {
          "claim_number": 14,
          "claim_type": "independent",
          "change_type": "삭제",
          "change_code": "D",
          "text": "",
          "refers_to": []
        },
        {
          "claim_number": 15,
          "claim_type": "independent",
          "change_type": "삭제",
          "change_code": "D",
          "text": "",
          "refers_to": []
        },
        {
          "claim_number": 16,
          "claim_type": "independent",
          "change_type": "삭제",
          "change_code": "D",
          "text": "",
          "refers_to": []
        },
        {
          "claim_number": 17,
          "claim_type": "independent",
          "change_type": "삭제",
          "change_code": "D",
          "text": "",
          "refers_to": []
        },
        {
          "claim_number": 18,
          "claim_type": "independent",
          "change_type": "삭제",
          "change_code": "D",
          "text": "",
          "refers_to": []
        },
        {
          "claim_number": 19,
          "claim_type": "independent",
          "change_type": "삭제",
          "change_code": "D",
          "text": "",
          "refers_to": []
        },
        {
          "claim_number": 20,
          "claim_type": "independent",
          "change_type": "삭제",
          "change_code": "D",
          "text": "",
          "refers_to": []
        },
        {
          "claim_number": 21,
          "claim_type": "independent",
          "change_type": "삭제",
          "change_code": "D",
          "text": "",
          "refers_to": []
        },
        {
          "claim_number": 22,
          "claim_type": "independent",
          "change_type": "삭제",
          "change_code": "D",
          "text": "",
          "refers_to": []
        },
        {
          "claim_number": 23,
          "claim_type": "independent",
          "change_type": "삭제",
          "change_code": "D",
          "text": "",
          "refers_to": []
        },
        {
          "claim_number": 24,
          "claim_type": "independent",
          "change_type": "삭제",
          "change_code": "D",
          "text": "",
          "refers_to": []
        },
        {
          "claim_number": 25,
          "claim_type": "independent",
          "change_type": "삭제",
          "change_code": "D",
          "text": "",
          "refers_to": []
        },
        {
          "claim_number": 26,
          "claim_type": "independent",
          "change_type": "삭제",
          "change_code": "D",
          "text": "",
          "refers_to": []
        },
        {
          "claim_number": 27,
          "claim_type": "independent",
          "change_type": "삭제",
          "change_code": "D",
          "text": "",
          "refers_to": []
        },
        {
          "claim_number": 28,
          "claim_type": "independent",
          "change_type": "삭제",
          "change_code": "D",
          "text": "",
          "refers_to": []
        },
        {
          "claim_number": 29,
          "claim_type": "independent",
          "change_type": "삭제",
          "change_code": "D",
          "text": "",
          "refers_to": []
        },
        {
          "claim_number": 30,
          "claim_type": "independent",
          "change_type": "삭제",
          "change_code": "D",
          "text": "",
          "refers_to": []
        },
        {
          "claim_number": 31,
          "claim_type": "independent",
          "change_type": "삭제",
          "change_code": "D",
          "text": "",
          "refers_to": []
        },
        {
          "claim_number": 32,
          "claim_type": "independent",
          "change_type": "삭제",
          "change_code": "D",
          "text": "",
          "refers_to": []
        },
        {
          "claim_number": 33,
          "claim_type": "independent",
          "change_type": "삭제",
          "change_code": "D",
          "text": "",
          "refers_to": []
        },
        {
          "claim_number": 34,
          "claim_type": "independent",
          "change_type": "삭제",
          "change_code": "D",
          "text": "",
          "refers_to": []
        },
        {
          "claim_number": 35,
          "claim_type": "independent",
          "change_type": "삭제",
          "change_code": "D",
          "text": "",
          "refers_to": []
        },
        {
          "claim_number": 36,
          "claim_type": "independent",
          "change_type": "삭제",
          "change_code": "D",
          "text": "",
          "refers_to": []
        },
        {
          "claim_number": 37,
          "claim_type": "independent",
          "change_type": "삭제",
          "change_code": "D",
          "text": "",
          "refers_to": []
        },
        {
          "claim_number": 38,
          "claim_type": "independent",
          "change_type": "삭제",
          "change_code": "D",
          "text": "",
          "refers_to": []
        },
        {
          "claim_number": 39,
          "claim_type": "independent",
          "change_type": "삭제",
          "change_code": "D",
          "text": "",
          "refers_to": []
        },
        {
          "claim_number": 40,
          "claim_type": "independent",
          "change_type": "삭제",
          "change_code": "D",
          "text": "",
          "refers_to": []
        },
        {
          "claim_number": 41,
          "claim_type": "independent",
          "change_type": "삭제",
          "change_code": "D",
          "text": "",
          "refers_to": []
        },
        {
          "claim_number": 42,
          "claim_type": "independent",
          "change_type": "삭제",
          "change_code": "D",
          "text": "",
          "refers_to": []
        },
        {
          "claim_number": 43,
          "claim_type": "independent",
          "change_type": "삭제",
          "change_code": "D",
          "text": "",
          "refers_to": []
        },
        {
          "claim_number": 44,
          "claim_type": "independent",
          "change_type": "삭제",
          "change_code": "D",
          "text": "",
          "refers_to": []
        },
        {
          "claim_number": 45,
          "claim_type": "independent",
          "change_type": "삭제",
          "change_code": "D",
          "text": "",
          "refers_to": []
        },
        {
          "claim_number": 46,
          "claim_type": "independent",
          "change_type": "삭제",
          "change_code": "D",
          "text": "",
          "refers_to": []
        },
        {
          "claim_number": 47,
          "claim_type": "independent",
          "change_type": "삭제",
          "change_code": "D",
          "text": "",
          "refers_to": []
        },
        {
          "claim_number": 48,
          "claim_type": "independent",
          "change_type": "삭제",
          "change_code": "D",
          "text": "",
          "refers_to": []
        },
        {
          "claim_number": 49,
          "claim_type": "independent",
          "change_type": "삭제",
          "change_code": "D",
          "text": "",
          "refers_to": []
        },
        {
          "claim_number": 50,
          "claim_type": "independent",
          "change_type": "삭제",
          "change_code": "D",
          "text": "",
          "refers_to": []
        },
        {
          "claim_number": 51,
          "claim_type": "independent",
          "change_type": "삭제",
          "change_code": "D",
          "text": "",
          "refers_to": []
        },
        {
          "claim_number": 52,
          "claim_type": "independent",
          "change_type": "삭제",
          "change_code": "D",
          "text": "",
          "refers_to": []
        },
        {
          "claim_number": 53,
          "claim_type": "independent",
          "change_type": "삭제",
          "change_code": "D",
          "text": "",
          "refers_to": []
        },
        {
          "claim_number": 54,
          "claim_type": "independent",
          "change_type": "삭제",
          "change_code": "D",
          "text": "",
          "refers_to": []
        },
        {
          "claim_number": 55,
          "claim_type": "independent",
          "change_type": "삭제",
          "change_code": "D",
          "text": "",
          "refers_to": []
        },
        {
          "claim_number": 56,
          "claim_type": "independent",
          "change_type": "삭제",
          "change_code": "D",
          "text": "",
          "refers_to": []
        },
        {
          "claim_number": 57,
          "claim_type": "independent",
          "change_type": "삭제",
          "change_code": "D",
          "text": "",
          "refers_to": []
        },
        {
          "claim_number": 58,
          "claim_type": "independent",
          "change_type": "삭제",
          "change_code": "D",
          "text": "",
          "refers_to": []
        },
        {
          "claim_number": 59,
          "claim_type": "independent",
          "change_type": "삭제",
          "change_code": "D",
          "text": "",
          "refers_to": []
        },
        {
          "claim_number": 60,
          "claim_type": "independent",
          "change_type": "삭제",
          "change_code": "D",
          "text": "",
          "refers_to": []
        },
        {
          "claim_number": 61,
          "claim_type": "independent",
          "change_type": "삭제",
          "change_code": "D",
          "text": "",
          "refers_to": []
        },
        {
          "claim_number": 62,
          "claim_type": "independent",
          "change_type": "삭제",
          "change_code": "D",
          "text": "",
          "refers_to": []
        },
        {
          "claim_number": 63,
          "claim_type": "independent",
          "change_type": "삭제",
          "change_code": "D",
          "text": "",
          "refers_to": []
        },
        {
          "claim_number": 64,
          "claim_type": "independent",
          "change_type": "삭제",
          "change_code": "D",
          "text": "",
          "refers_to": []
        },
        {
          "claim_number": 65,
          "claim_type": "independent",
          "change_type": "삭제",
          "change_code": "D",
          "text": "",
          "refers_to": []
        },
        {
          "claim_number": 66,
          "claim_type": "independent",
          "change_type": "삭제",
          "change_code": "D",
          "text": "",
          "refers_to": []
        },
        {
          "claim_number": 67,
          "claim_type": "independent",
          "change_type": "삭제",
          "change_code": "D",
          "text": "",
          "refers_to": []
        },
        {
          "claim_number": 68,
          "claim_type": "independent",
          "change_type": "삭제",
          "change_code": "D",
          "text": "",
          "refers_to": []
        },
        {
          "claim_number": 69,
          "claim_type": "independent",
          "change_type": "삭제",
          "change_code": "D",
          "text": "",
          "refers_to": []
        },
        {
          "claim_number": 70,
          "claim_type": "independent",
          "change_type": "삭제",
          "change_code": "D",
          "text": "",
          "refers_to": []
        },
        {
          "claim_number": 71,
          "claim_type": "independent",
          "change_type": "삭제",
          "change_code": "D",
          "text": "",
          "refers_to": []
        },
        {
          "claim_number": 72,
          "claim_type": "independent",
          "change_type": "삭제",
          "change_code": "D",
          "text": "",
          "refers_to": []
        }
      ]
    },
    "all_versions": [
      {
        "version": 1,
        "receipt_date": "20160321",
        "document_name": "[특허출원]특허법 제203조에 따른 서면",
        "claim_count": 72,
        "claims": [
          {
            "claim_number": 1,
            "claim_type": "independent",
            "change_type": "신규",
            "change_code": "I",
            "text": "인간 혈액-유도된 혈소판 농축물의 생물활성 분획을 포함하는 조성물로서,\n상기 혈소판 농축물은 인간 혈소판과 인간 혈장을 포함하며, 상기 생물활성 분획은 피브리노겐, 알부민, 글로불린, 및 적어도 하나의 TGF-β1, EGF, FGF-염기성, PDGF-AA, PDGF-BB, SDF-1α, 및 VEGF이 포함된 상기 혈소판 농축물의 원상태 성분을 포함하는, 조성물.",
            "refers_to": []
          },
          {
            "claim_number": 2,
            "claim_type": "dependent",
            "change_type": "신규",
            "change_code": "I",
            "text": "청구항 1에 있어서, 상기 피브리노겐은 20,000 ng/mL 미만의 수준으로 존재하는, 조성물.",
            "refers_to": [
              1
            ]
          },
          {
            "claim_number": 3,
            "claim_type": "independent",
            "change_type": "신규",
            "change_code": "I",
            "text": "청구항 1 또는 2에 있어서, 각각의 상기 TGF-β1, EGF, FGF-염기성, PDGF-AA, PDGF-BB, SDF-1α, 및 VEGF를 포함하는, 조성물.",
            "refers_to": []
          },
          {
            "claim_number": 4,
            "claim_type": "independent",
            "change_type": "신규",
            "change_code": "I",
            "text": "상기 항에 있어서, 본 조성물은 본질적으로 헤파린이 없는, 조성물.",
            "refers_to": []
          },
          {
            "claim_number": 5,
            "claim_type": "independent",
            "change_type": "신규",
            "change_code": "I",
            "text": "상기 항에 있어서, 상기 생물활성 분획은 상기 혈소판 농축물에 대하여 원상태인 IL-1b, IL-6, IL-8, IL-10, IL-13, IL-17, IFN-감마, 및 TNF-알파중 적어도 하나, 그리고 바람직하게는 이들 각각을 또한 포함하는, 조성물.",
            "refers_to": []
          },
          {
            "claim_number": 6,
            "claim_type": "independent",
            "change_type": "신규",
            "change_code": "I",
            "text": "상기 항에 있어서, 상기 생물활성 분획은 액체 생물활성 분획이며, 여기서 상기 조성물은 다음을 포함하는 조성물:\n약 0.5 내지 2.5 g/dL의 글로불린, 바람직하게는 약 1 내지 2 g/dL의 글로불린;\n약 2 내지 5 g/dL의 알부민, 바람직하게는 약 3 내지 4 g/dL의 알부민;\n약 100 내지 200 mmol/L의 나트륨, 바람직하게는 약 120 내지 약 160 mmol/L의 나트륨;\n약 50 내지 120 mg/dL의 트리글리세라이드, 바람직하게는 약 60 내지 110 mg/dL의 트리글리세라이드; 및/또는\n약 150 내지 300 mg/dL의 글루코오스, 바람직하게는 약 150 내지 250 mg/dL의 글루코오스.",
            "refers_to": []
          },
          {
            "claim_number": 7,
            "claim_type": "independent",
            "change_type": "신규",
            "change_code": "I",
            "text": "상기 항에 있어서, 세제 잔유물이 없는, 조성물.",
            "refers_to": []
          },
          {
            "claim_number": 8,
            "claim_type": "independent",
            "change_type": "신규",
            "change_code": "I",
            "text": "상기 항에 있어서, 상기 생물활성 분획은 액체 생물활성 분획이며, 여기서 상기 PDGF-BB 농도는 1000 pg/mL 미만인, 조성물.",
            "refers_to": []
          },
          {
            "claim_number": 9,
            "claim_type": "independent",
            "change_type": "신규",
            "change_code": "I",
            "text": "상기 항에 있어서, 상기 생물활성 분획은 액체 생물활성 분획이며, 여기서 상기 PDGF-AA 농도는 3000 pg/mL 미만인, 조성물.",
            "refers_to": []
          },
          {
            "claim_number": 10,
            "claim_type": "independent",
            "change_type": "신규",
            "change_code": "I",
            "text": "상기 항에 있어서, 상기 생물활성 분획은 액체 생물활성 분획이며, 여기서 상기 TGF-β1 농도는 적어도 5000 pg/mL인, 조성물.",
            "refers_to": []
          },
          {
            "claim_number": 11,
            "claim_type": "independent",
            "change_type": "신규",
            "change_code": "I",
            "text": "상기 항에 있어서, 상기 생물활성 분획은 액체 생물활성 분획이며, 여기서 상기 VEGF 농도는 300 pg/mL 미만인, 조성물.",
            "refers_to": []
          },
          {
            "claim_number": 12,
            "claim_type": "independent",
            "change_type": "신규",
            "change_code": "I",
            "text": "상기 항에 있어서, 상기 생물활성 분획은 액체 생물활성 분획이며, 여기서 상기 원상태 성분은 하기를 포함하는, 조성물:\n상기 액체 생물활성 분획의 20,000 ng/ml 미만 수준에서 피브리노겐;\n상기 액체 생물활성 분획의 적어도 2 mg/dL 수준에서 알부민;\n상기 액체 생물활성 분획의 적어도 1 g/dL 수준에서 글로불린;\n상기 액체 생물활성 분획의 적어도 5000 pg/mL 수준에서 TGF-β1;\n상기 액체 생물활성 분획의 적어도 20 pg/mL 수준에서 EGF;\n상기 액체 생물활성 분획의 적어도 5 pg/mL 수준에서 FGF-베타;\n상기 액체 생물활성 분획의 적어도 200 pg/mL 수준에서 PDGF-AA;\n상기 액체 생물활성 분획의 적어도 50 pg/mL 수준에서 PDGF-BB;\n상기 액체 생물활성 분획의 적어도 100 pg/mL 수준에서 SDF-1α; 및\n상기 액체 생물활성 분획의 적어도 10 pg/mL 수준에서 VEGF.",
            "refers_to": []
          },
          {
            "claim_number": 13,
            "claim_type": "independent",
            "change_type": "신규",
            "change_code": "I",
            "text": "상기 항에 있어서,\n상기 조성물은 260-340 mmol/kg 범위의 오스몰농도를 갖는, 조성물.",
            "refers_to": []
          },
          {
            "claim_number": 14,
            "claim_type": "independent",
            "change_type": "신규",
            "change_code": "I",
            "text": "상기 항에 있어서, \n상기 조성물은 6.8 내지 7.8 범위의 pH를 갖는, 조성물.",
            "refers_to": []
          },
          {
            "claim_number": 15,
            "claim_type": "independent",
            "change_type": "신규",
            "change_code": "I",
            "text": "상기 항에 있어서,\n본 조성물은 상기 혈소판 농축물에 대하여 원상태가 아닌 헤파린은 포함하지 않는, 조성물.",
            "refers_to": []
          },
          {
            "claim_number": 16,
            "claim_type": "independent",
            "change_type": "신규",
            "change_code": "I",
            "text": "청구항 1 내지 15중 임의의 하나에 따른 조성물을 포함하는 세포 배양 배지.",
            "refers_to": []
          },
          {
            "claim_number": 17,
            "claim_type": "dependent",
            "change_type": "신규",
            "change_code": "I",
            "text": "청구항 16에 있어서, 헤파린이 없는 세포 배양 배지.",
            "refers_to": [
              16
            ]
          },
          {
            "claim_number": 18,
            "claim_type": "independent",
            "change_type": "신규",
            "change_code": "I",
            "text": "생물활성 조성물을 제조하는 방법에서, 이 방법은\n응고 물질을 혈소판 용해물 조성물에 부가하여, 응고된 물질을 만들고;\n상기 응고된 물질 안의 액체로부터 응고된 고형물을 분리시키고; 및\n상기 액체는 심층 여과를 거치는 것을 포함하는, 방법.",
            "refers_to": []
          },
          {
            "claim_number": 19,
            "claim_type": "dependent",
            "change_type": "신규",
            "change_code": "I",
            "text": "청구항 18에 있어서, \n상기 심층 여과는 양성 표면 전하를 갖는 심층 여과 매질로 수행되는, 방법.",
            "refers_to": [
              18
            ]
          },
          {
            "claim_number": 20,
            "claim_type": "independent",
            "change_type": "신규",
            "change_code": "I",
            "text": "청구항 18 또는 19에 있어서, \n상기 응고 물질은 염화칼슘 염을 포함하는, 방법.",
            "refers_to": []
          },
          {
            "claim_number": 21,
            "claim_type": "independent",
            "change_type": "신규",
            "change_code": "I",
            "text": "청구항 18 내지 20중 임의의 한 항에 있어서, \n상기 액체는 멸균 여과를 거치는 것을 또한 포함하는, 방법.",
            "refers_to": []
          },
          {
            "claim_number": 22,
            "claim_type": "independent",
            "change_type": "신규",
            "change_code": "I",
            "text": "청구항 18 내지 21중 임의의 한 항에 있어서,\n상기 혈소판 용해물 조성물은 이 안에 혈소판을 용해시키기 위하여 혈소판 농축물 조성물을 냉동하고, 해동하는 것이 포함된 공정에 의해 제조되는, 방법.",
            "refers_to": []
          },
          {
            "claim_number": 23,
            "claim_type": "dependent",
            "change_type": "신규",
            "change_code": "I",
            "text": "청구항 22에 있어서, \n상기 혈소판 농축물 조성물은 혈소판 및 혈장이 포함된 성분채집된 인간 혈소판 조성물을 포함하는, 방법.",
            "refers_to": [
              22
            ]
          },
          {
            "claim_number": 24,
            "claim_type": "independent",
            "change_type": "신규",
            "change_code": "I",
            "text": "청구항 18 내지 23중 임의의 한 항에 있어서, \n멸균된 용기 안에 상기 생물활성 조성물을 패키징하는 것을 또한 포함하는, 방법.",
            "refers_to": []
          },
          {
            "claim_number": 25,
            "claim_type": "independent",
            "change_type": "신규",
            "change_code": "I",
            "text": "환자, 임의로 인간 환자를 치료하는 방법에서, \n청구항 1 내지 15중 임의의 한 항에 따른 상기 조성물이 포함된 치료적 물질을 투여하는 것을 포함하는, 방법.",
            "refers_to": []
          },
          {
            "claim_number": 26,
            "claim_type": "independent",
            "change_type": "신규",
            "change_code": "I",
            "text": "생물활성 조성물을 제조하는 방법에서, \n혈소판 및 혈장이 포함된 인간 혈액-유도된 농축물의 혈소판을 용해시켜, 용해된 혈소판 제조물을 만들고;\n상기 용해된 혈소판 제조물 안에 피브리노겐을 피브린으로 전환시킴으로써 용해된 혈소판 제조물로부터 겔 응고를 형성시키고;\n상기 겔 응고로부터 액체를 빼내기 위하여 상기 겔 응고를 압착시키고; 및\n상기 겔 응고 고형물로부터 상기 액체를 분리시키는 것을 포함하는, 방법.",
            "refers_to": []
          },
          {
            "claim_number": 27,
            "claim_type": "independent",
            "change_type": "신규",
            "change_code": "I",
            "text": "혈소판 용해물 조성물을 가공하는 방법에서, \n혈소판 및 혈장이 포함된 인간 혈액-유도된 농축물의 혈소판을 용해시켜, 용해된 혈소판 제조물을 만들고;\n용해된 혈소판 제조물 안에 피브리노겐을 피브린으로 전환시켜 형성된 겔 응고를 압착시켜, 상기 겔 응고로부터 액체를 뽑아내는 것을 포함하는, 방법.",
            "refers_to": []
          },
          {
            "claim_number": 28,
            "claim_type": "independent",
            "change_type": "신규",
            "change_code": "I",
            "text": "혈소판 용해물 조성물을 가공하는 방법에서, 이 방법은 \n상기 액체 생물활성 분획으로부터 현탁된 고형물을 제거하기 위하여, 피브리노겐, 알부민, 글로불린, TGF-β1, EGF, FGF-베타, PDGF-AA, PDGF-BB, SDF-1α, 및 VEGF가 포함된 상기 혈소판 농축물의 원상태 성분을 포함하는 액체 인간 혈액-유도된 혈소판 농축물의 생물활성 분획을 적어도 제1 심층 필터를 통하여 통과시키는 것을 포함하고, 여기서 상기 피브리노겐은 20,000 ng/mL 미만 수준으로 존재하는, 방법.",
            "refers_to": []
          },
          {
            "claim_number": 29,
            "claim_type": "dependent",
            "change_type": "신규",
            "change_code": "I",
            "text": "청구항 28에 있어서, 상기 농축물의 액체 생물활성 분획으로부터 농축물의 응고된 분획을 분리시키기 위하여 원심분리 단계없이, 혈액-유도된 혈소판 농축물로부터 상기 액체 생물활성 분획을 획득하는 것을 더 포함하는, 방법.",
            "refers_to": [
              28
            ]
          },
          {
            "claim_number": 30,
            "claim_type": "dependent",
            "change_type": "신규",
            "change_code": "I",
            "text": "청구항 28에 있어서, 상기 획득은\n상기 농축물의 혈소판을 용해시켜 용해된 제조물을 만들고;\n상기 용해된 제조물의 피브리노겐을 피브린으로 전환시켜, 겔 응고를 만들고; 그리고\n원심분리 없이 상기 겔 응고를 압착시켜, 겔 응고로부터 상기 액체 생물활성 분획을 빼내는 것을 포함하는, 방법.",
            "refers_to": [
              28
            ]
          },
          {
            "claim_number": 31,
            "claim_type": "dependent",
            "change_type": "신규",
            "change_code": "I",
            "text": "청구항 30에 있어서, 상기 압착은 제1 표면과 제2 표면 사이에 접촉된 상기 겔 응고를 압착시켜, 상기 겔 응고로부터 상기 액체 생물활성 분획은 빼내고, 고형 응고 덩어리는 남아있게 하는 것을 포함하는, 방법.",
            "refers_to": [
              30
            ]
          },
          {
            "claim_number": 32,
            "claim_type": "independent",
            "change_type": "신규",
            "change_code": "I",
            "text": "청구항 28-31중 임의의 한 항에 있어서, 상기 통과에 의해 \nTGF-베타-1, EGF, FGF-b, PDGF-AA, PDGF-BB, SDF-1α, 및 VEGF 중 하나, 일부 또는 모두의 수준이 적어도 20% 감소; 및/또는\nTGF-베타-1의 수준이 적어도 50% 감소; 및/또는\nEGF의 수준이 적어도 30% 감소; 및/또는\nFGF-b의 수준이 적어도 20% 감소; 및/또는\nPDGF-AA의 수준이 적어도 50% 감소; 및/또는\nPDGF-BB의 수준이 적어도 50% 감소; 및/또는\nSDF-1α의 수준이 적어도 20% 감소; 및/또는\nVEGF의 수준이 적어도 30% 감소를 초래하는, 방법.",
            "refers_to": []
          },
          {
            "claim_number": 33,
            "claim_type": "independent",
            "change_type": "신규",
            "change_code": "I",
            "text": "세포를 동결보존하는 방법에서, \n청구항 1-15중 임의의 한 항에 따른 조성물이 포함된 세포 조성물을 냉동보존 조건에 두는 것을 포함하는, 방법.",
            "refers_to": []
          },
          {
            "claim_number": 34,
            "claim_type": "independent",
            "change_type": "신규",
            "change_code": "I",
            "text": "청구항 1-16중 임의의 한 항에 있어서, 상기 조성물은 액체 전달 장치 안에 보관된, 조성물.",
            "refers_to": []
          },
          {
            "claim_number": 35,
            "claim_type": "dependent",
            "change_type": "신규",
            "change_code": "I",
            "text": "청구항 34에 있어서, 상기 액체 전달 장치는 점안기를 포함하는, 조성물.",
            "refers_to": [
              34
            ]
          },
          {
            "claim_number": 36,
            "claim_type": "independent",
            "change_type": "신규",
            "change_code": "I",
            "text": "청구항 1-16중 임의의 한 항에 있어서 여기서 상기 조성물은 갯과 환자에서 질환 또는 병든 상태를 치료하는데 효과적인, 조성물.",
            "refers_to": []
          },
          {
            "claim_number": 37,
            "claim_type": "dependent",
            "change_type": "신규",
            "change_code": "I",
            "text": "청구항 36에 있어서, 상기 병든 상태는 건성각결막염을 포함하는, 조성물.",
            "refers_to": [
              36
            ]
          },
          {
            "claim_number": 38,
            "claim_type": "dependent",
            "change_type": "신규",
            "change_code": "I",
            "text": "청구항 1에 있어서, 상기 생물활성 분획은 액체 생물활성 분획이며, 그리고 여기서 본 조성물은 하기를 포함하는 조성물:\n약 200 pg/mL 내지 약 350 pg/mL 수준에서 FGF-2;\n약 1800 pg/mL 내지 약 3100 pg/mL 수준에서 EGF; \n약 24,000 pg/mL 내지 약 28,000 pg/mL 수준에서 PDGF-AA; \n약 50 ng/mL 내지 약 80 ng/mL 수준에서 PDGF-BB; \n약 500 pg/mL 내지 약 800 pg/mL 수준에서 VEGF; \n약 60 ng/mL 내지 약 90 ng/mL 수준에서 TGF-b; 그리고\n미만 2.5㎍/mL 미만의 수준에서 피브리노겐.",
            "refers_to": [
              1
            ]
          },
          {
            "claim_number": 39,
            "claim_type": "dependent",
            "change_type": "신규",
            "change_code": "I",
            "text": "청구항 1에 있어서, 상기 피브리노겐은 20,000 ng/mL 미만 수준으로 존재하는, 조성물.",
            "refers_to": [
              1
            ]
          },
          {
            "claim_number": 40,
            "claim_type": "dependent",
            "change_type": "신규",
            "change_code": "I",
            "text": "청구항 1에 있어서, 각각의 상기 TGF-β1, EGF, FGF-염기성, PDGF-AA, PDGF-BB, SDF-1α, 및 VEGF를 포함하는, 조성물.",
            "refers_to": [
              1
            ]
          },
          {
            "claim_number": 41,
            "claim_type": "dependent",
            "change_type": "신규",
            "change_code": "I",
            "text": "청구항 1에 있어서, 상기 조성물은 본질적으로 헤파린이 없는, 조성물.",
            "refers_to": [
              1
            ]
          },
          {
            "claim_number": 42,
            "claim_type": "dependent",
            "change_type": "신규",
            "change_code": "I",
            "text": "청구항 1에 있어서, 상기 생물활성 분획은 상기 혈소판 농축물에 원상태인 IL-1b, IL-6, IL-8, IL-10, IL-13, IL-17, IFN-감마, 및 TNF-알파중 적어도 하나, 그리고 바람직하게는 이들 각각을 또한 포함하는, 조성물.",
            "refers_to": [
              1
            ]
          },
          {
            "claim_number": 43,
            "claim_type": "dependent",
            "change_type": "신규",
            "change_code": "I",
            "text": "청구항 1에 있어서, 상기 생물활성 분획은 액체 생물활성 분획이며, 그리고 여기서 상기 조성물은 다음을 포함하는 조성물:\n약 0.5 내지 2.5 g/dL의 글로불린, 바람직하게는 약 1 내지 2 g/dL의 글로불린;\n약 2 내지 5 g/dL의 알부민, 바람직하게는 약 3 내지 4 g/dL의 알부민;\n약 100 내지 200 mmol/L의 나트륨, 바람직하게는 약 120 내지 약 160 mmol/L의 나트륨;\n약 50 내지 120 mg/dL의 트리글리세라이드, 바람직하게는 약 60 내지 110 mg/dL의 트리글리세라이드; 및/또는\n약 150 내지 300 mg/dL의 글루코오스, 바람직하게는 약 150 내지 250 mg/dL의 글루코오스.",
            "refers_to": [
              1
            ]
          },
          {
            "claim_number": 44,
            "claim_type": "dependent",
            "change_type": "신규",
            "change_code": "I",
            "text": "청구항 1에 있어서, 세제 잔유물이 없는, 조성물.",
            "refers_to": [
              1
            ]
          },
          {
            "claim_number": 45,
            "claim_type": "dependent",
            "change_type": "신규",
            "change_code": "I",
            "text": "청구항 1에 있어서, 상기 생물활성 분획은 액체 생물활성 분획이며, 그리고 여기서 상기 PDGF-BB 농도는 1000 pg/mL 미만인, 조성물.",
            "refers_to": [
              1
            ]
          },
          {
            "claim_number": 46,
            "claim_type": "dependent",
            "change_type": "신규",
            "change_code": "I",
            "text": "청구항 1에 있어서, 상기 생물활성 분획은 액체 생물활성 분획이며, 그리고 여기서 상기 PDGF-AA 농도는 3000 pg/mL 미만인, 조성물.",
            "refers_to": [
              1
            ]
          },
          {
            "claim_number": 47,
            "claim_type": "dependent",
            "change_type": "신규",
            "change_code": "I",
            "text": "청구항 1에 있어서, 상기 생물활성 분획은 액체 생물활성 분획이며, 그리고 여기서 상기 TGF-β1 농도는 적어도 5000 pg/mL인, 조성물.",
            "refers_to": [
              1
            ]
          },
          {
            "claim_number": 48,
            "claim_type": "dependent",
            "change_type": "신규",
            "change_code": "I",
            "text": "청구항 1에 있어서, 상기 생물활성 분획은 액체 생물활성 분획이며, 그리고 여기서 상기 VEGF 농도는 300 pg/mL 미만인, 조성물.",
            "refers_to": [
              1
            ]
          },
          {
            "claim_number": 49,
            "claim_type": "dependent",
            "change_type": "신규",
            "change_code": "I",
            "text": "청구항 1에 있어서, 상기 생물활성 분획은 액체 생물활성 분획이며, 그리고 여기서 상기 원상태 성분은 하기를 포함하는, 조성물:\n상기 액체 생물활성 분획의 20,000 ng/ml 미만 수준에서 피브리노겐;\n상기 액체 생물활성 분획의 적어도 2 mg/dL 수준에서 알부민;\n상기 액체 생물활성 분획의 적어도 1 g/dL 수준에서 글로불린;\n상기 액체 생물활성 분획의 적어도 5000 pg/mL 수준에서 TGF-β1 ;\n상기 액체 생물활성 분획의 적어도 20 pg/mL 수준에서 EGF;\n상기 액체 생물활성 분획의 적어도 5 pg/mL 수준에서 FGF-베타;\n상기 액체 생물활성 분획의 적어도 200 pg/mL 수준에서 PDGF-AA;\n상기 액체 생물활성 분획의 적어도 50 pg/mL 수준에서 PDGF-BB;\n상기 액체 생물활성 분획의 적어도 100 pg/mL 수준에서 SDF-1α; 그리고\n상기 액체 생물활성 분획의 적어도 10 pg/mL 수준에서 VEGF.",
            "refers_to": [
              1
            ]
          },
          {
            "claim_number": 50,
            "claim_type": "dependent",
            "change_type": "신규",
            "change_code": "I",
            "text": "청구항 1에 있어서, \n상기 조성물은 260-340 mmol/kg 범위의 오스몰농도를 갖는, 조성물",
            "refers_to": [
              1
            ]
          },
          {
            "claim_number": 51,
            "claim_type": "dependent",
            "change_type": "신규",
            "change_code": "I",
            "text": "청구항 1에 있어서, \n상기 조성물은 6.8 내지 7.8 범위의 pH를 갖는, 조성물.",
            "refers_to": [
              1
            ]
          },
          {
            "claim_number": 52,
            "claim_type": "dependent",
            "change_type": "신규",
            "change_code": "I",
            "text": "청구항 1에 있어서, \n본 조성물은 상기 혈소판 농축물에 대하여 원상태가 아닌 헤파린은 포함하지 않는, 조성물.",
            "refers_to": [
              1
            ]
          },
          {
            "claim_number": 53,
            "claim_type": "dependent",
            "change_type": "신규",
            "change_code": "I",
            "text": "청구항 1 에 따른 조성물을 포함하는 세포 배양 배지.",
            "refers_to": [
              1
            ]
          },
          {
            "claim_number": 54,
            "claim_type": "dependent",
            "change_type": "신규",
            "change_code": "I",
            "text": "청구항 51에 있어서, 헤파린이 없는 세포 배양 배지.",
            "refers_to": [
              51
            ]
          },
          {
            "claim_number": 55,
            "claim_type": "dependent",
            "change_type": "신규",
            "change_code": "I",
            "text": "청구항 18에 있어서, \n상기 심층 여과는 양성 표면 전하를 갖는 심층 여과 매질로 수행되는, 방법.",
            "refers_to": [
              18
            ]
          },
          {
            "claim_number": 56,
            "claim_type": "dependent",
            "change_type": "신규",
            "change_code": "I",
            "text": "청구항 18에 있어서, \n상기 응고 물질은 염화칼슘 염을 포함하는, 방법.",
            "refers_to": [
              18
            ]
          },
          {
            "claim_number": 57,
            "claim_type": "dependent",
            "change_type": "신규",
            "change_code": "I",
            "text": "청구항 18에 있어서, \n상기 액체는 멸균 여과를 거치는 것을 또한 포함하는, 방법.",
            "refers_to": [
              18
            ]
          },
          {
            "claim_number": 58,
            "claim_type": "dependent",
            "change_type": "신규",
            "change_code": "I",
            "text": "청구항 18에 있어서,\n상기 혈소판 용해물 조성물은 이 안에 혈소판을 용해시키기 위하여 혈소판 농축물 조성물을 냉동하고, 해동하는 것이 포함된 공정에 의해 제조되는, 방법.",
            "refers_to": [
              18
            ]
          },
          {
            "claim_number": 59,
            "claim_type": "dependent",
            "change_type": "신규",
            "change_code": "I",
            "text": "청구항 58에 있어서, \n상기 혈소판 농축물 조성물은 혈소판 및 혈장이 포함된 성분채집된 인간 혈소판 조성물을 포함하는, 방법.",
            "refers_to": [
              58
            ]
          },
          {
            "claim_number": 60,
            "claim_type": "dependent",
            "change_type": "신규",
            "change_code": "I",
            "text": "청구항 18에 있어서, \n멸균된 용기 안에 상기 생물활성 조성물을 패키징하는 것을 또한 포함하는, 방법.",
            "refers_to": [
              18
            ]
          },
          {
            "claim_number": 61,
            "claim_type": "dependent",
            "change_type": "신규",
            "change_code": "I",
            "text": "환자, 임의로 인간 환자를 치료하는 방법에서, \n청구항 1 에 따른 상기 조성물이 포함된 치료적 물질을 투여하는 것을 포함하는, 방법.",
            "refers_to": [
              1
            ]
          },
          {
            "claim_number": 62,
            "claim_type": "dependent",
            "change_type": "신규",
            "change_code": "I",
            "text": "청구항 28에 있어서, \n여기서 상기 통과에 의해 \nTGF-베타-1, EGF, FGF-b, PDGF-AA, PDGF-BB, SDF-1α, 및 VEGF 중 하나, 일부 또는 모두의 수준이 적어도 20% 감소; 및/또는\nTGF-베타-1의 수준이 적어도 50% 감소; 및/또는\nEGF의 수준이 적어도 30% 감소; 및/또는\nFGF-b의 수준이 적어도 20% 감소; 및/또는\nPDGF-AA의 수준이 적어도 50% 감소; 및/또는\nPDGF-BB의 수준이 적어도 50% 감소; 및/또는\nSDF-1α의 수준이 적어도 20% 감소; 및/또는\nVEGF의 수준이 적어도 30% 감소를 초래하는, 방법.",
            "refers_to": [
              28
            ]
          },
          {
            "claim_number": 63,
            "claim_type": "dependent",
            "change_type": "신규",
            "change_code": "I",
            "text": "세포를 동결보존하는 방법에서, \n청구항 1에 따른 조성물이 포함된 세포 조성물을 냉동보존 조건에 두는 것을 포함하는, 방법.",
            "refers_to": [
              1
            ]
          },
          {
            "claim_number": 64,
            "claim_type": "dependent",
            "change_type": "신규",
            "change_code": "I",
            "text": "청구항 1에 있어서, 상기 조성물은 액체 전달 장치 안에 보관된, 조성물.",
            "refers_to": [
              1
            ]
          },
          {
            "claim_number": 65,
            "claim_type": "dependent",
            "change_type": "신규",
            "change_code": "I",
            "text": "청구항 64에 있어서, 상기 액체 전달 장치는 점안기를 포함하는, 조성물.",
            "refers_to": [
              64
            ]
          },
          {
            "claim_number": 66,
            "claim_type": "dependent",
            "change_type": "신규",
            "change_code": "I",
            "text": "청구항 1에 있어서, 상기 조성물은 갯과 환자에서 질환 또는 병든 상태를 치료하는데 효과적인, 조성물.",
            "refers_to": [
              1
            ]
          },
          {
            "claim_number": 67,
            "claim_type": "dependent",
            "change_type": "신규",
            "change_code": "I",
            "text": "청구항 66에 있어서, 상기 병든 상태는 건성각결막염을 포함하는, 조성물.",
            "refers_to": [
              66
            ]
          },
          {
            "claim_number": 68,
            "claim_type": "independent",
            "change_type": "신규",
            "change_code": "I",
            "text": "생물활성 조성물을 제조하는 방법에서, \n응고 물질을 혈소판 용해물 조성물에 부가하여 응고된 물질을 만들고;\n상기 응고된 물질로부터 응고된 고형물을 분리시키고; 그리고\n상기 액체는 여과를 거치는 것을 포함하는, 방법.",
            "refers_to": []
          },
          {
            "claim_number": 69,
            "claim_type": "dependent",
            "change_type": "신규",
            "change_code": "I",
            "text": "청구항 68에 있어서, \n상기 응고 물질은 염화칼슘 염을 포함하는, 방법.",
            "refers_to": [
              68
            ]
          },
          {
            "claim_number": 70,
            "claim_type": "dependent",
            "change_type": "신규",
            "change_code": "I",
            "text": "청구항 68에 있어서, \n상기 혈소판 용해물 조성물은 이 안에 혈소판을 용해시키기 위하여 혈소판 농축물 조성물을 냉동하고, 해동하는 것이 포함된 공정에 의해 제조되는, 방법.",
            "refers_to": [
              68
            ]
          },
          {
            "claim_number": 71,
            "claim_type": "dependent",
            "change_type": "신규",
            "change_code": "I",
            "text": "청구항 68에 있어서, \n상기 혈소판 농축물 조성물은 혈소판 및 혈장이 포함된 성분채집된 인간 혈소판 조성물을 포함하는, 방법.",
            "refers_to": [
              68
            ]
          },
          {
            "claim_number": 72,
            "claim_type": "dependent",
            "change_type": "신규",
            "change_code": "I",
            "text": "청구항 68에 있어서, \n멸균된 용기 안에 상기 생물활성 조성물을 패키징하는 것을 또한 포함하는, 방법.",
            "refers_to": [
              68
            ]
          }
        ]
      },
      {
        "version": 2,
        "receipt_date": "20190826",
        "document_name": "[명세서등 보정]보정서",
        "claim_count": 70,
        "claims": [
          {
            "claim_number": 1,
            "claim_type": "independent",
            "change_type": "수정",
            "change_code": "A",
            "text": "인간 혈액-유도된 혈소판 농축물의 생물활성 분획을 포함하는 조성물로서,\n상기 혈소판 농축물은 인간 혈소판과 인간 혈장을 포함하며, 상기 생물활성 분획은 피브리노겐, 알부민, 글로불린, 및 TGF-β1, EGF, FGF-염기성, PDGF-AA, PDGF-BB, SDF-1α, 및 VEGF 중 적어도 하나가 포함된 상기 혈소판 농축물의 원상태 성분을 포함하는, 조성물.",
            "refers_to": []
          },
          {
            "claim_number": 3,
            "claim_type": "dependent",
            "change_type": "수정",
            "change_code": "A",
            "text": "청구항 1에 있어서, 각각의 상기 TGF-β1, EGF, FGF-염기성, PDGF-AA, PDGF-BB, SDF-1α, 및 VEGF를 포함하는, 조성물.",
            "refers_to": [
              1
            ]
          },
          {
            "claim_number": 4,
            "claim_type": "dependent",
            "change_type": "수정",
            "change_code": "A",
            "text": "청구항 1 내지 3 중 어느 한 항에 있어서, 상기 조성물은 본질적으로 헤파린이 없는, 조성물.",
            "refers_to": [
              1,
              2,
              3
            ]
          },
          {
            "claim_number": 5,
            "claim_type": "dependent",
            "change_type": "수정",
            "change_code": "A",
            "text": "청구항 1 내지 3 중 어느 한 항에 있어서, 상기 생물활성 분획은 상기 혈소판 농축물에 대하여 원상태인 IL-1b, IL-6, IL-8, IL-10, IL-13, IL-17, IFN-감마, 및 TNF-알파중 적어도 하나, 그리고 바람직하게는 이들 각각을 또한 포함하는, 조성물.",
            "refers_to": [
              1,
              2,
              3
            ]
          },
          {
            "claim_number": 6,
            "claim_type": "dependent",
            "change_type": "수정",
            "change_code": "A",
            "text": "청구항 1 내지 3 중 어느 한 항에 있어서, 상기 생물활성 분획은 액체 생물활성 분획이며, 여기서 상기 조성물은 다음을 포함하는 조성물:\n약 0.5 내지 2.5 g/dL의 글로불린, 바람직하게는 약 1 내지 2 g/dL의 글로불린;\n약 2 내지 5 g/dL의 알부민, 바람직하게는 약 3 내지 4 g/dL의 알부민;\n약 100 내지 200 mmol/L의 나트륨, 바람직하게는 약 120 내지 약 160 mmol/L의 나트륨;\n약 50 내지 120 mg/dL의 트리글리세라이드, 바람직하게는 약 60 내지 110 mg/dL의 트리글리세라이드; 및/또는\n약 150 내지 300 mg/dL의 글루코오스, 바람직하게는 약 150 내지 250 mg/dL의 글루코오스.",
            "refers_to": [
              1,
              2,
              3
            ]
          },
          {
            "claim_number": 7,
            "claim_type": "dependent",
            "change_type": "수정",
            "change_code": "A",
            "text": "청구항 1 내지 3 중 어느 한 항에 있어서, 세제 잔유물이 없는, 조성물.",
            "refers_to": [
              1,
              2,
              3
            ]
          },
          {
            "claim_number": 8,
            "claim_type": "dependent",
            "change_type": "수정",
            "change_code": "A",
            "text": "청구항 1 내지 3 중 어느 한 항에 있어서, 상기 생물활성 분획은 액체 생물활성 분획이며, 여기서 상기 PDGF-BB 농도는 1000 pg/mL 미만인, 조성물.",
            "refers_to": [
              1,
              2,
              3
            ]
          },
          {
            "claim_number": 9,
            "claim_type": "dependent",
            "change_type": "수정",
            "change_code": "A",
            "text": "청구항 1 내지 3 중 어느 한 항에 있어서, 상기 생물활성 분획은 액체 생물활성 분획이며, 여기서 상기 PDGF-AA 농도는 3000 pg/mL 미만인, 조성물.",
            "refers_to": [
              1,
              2,
              3
            ]
          },
          {
            "claim_number": 10,
            "claim_type": "dependent",
            "change_type": "수정",
            "change_code": "A",
            "text": "청구항 1 내지 3 중 어느 한 항에 있어서, 상기 생물활성 분획은 액체 생물활성 분획이며, 여기서 상기 TGF-β1 농도는 적어도 5000 pg/mL인, 조성물.",
            "refers_to": [
              1,
              2,
              3
            ]
          },
          {
            "claim_number": 11,
            "claim_type": "dependent",
            "change_type": "수정",
            "change_code": "A",
            "text": "청구항 1 내지 3 중 어느 한 항에 있어서, 상기 생물활성 분획은 액체 생물활성 분획이며, 여기서 상기 VEGF 농도는 300 pg/mL 미만인, 조성물.",
            "refers_to": [
              1,
              2,
              3
            ]
          },
          {
            "claim_number": 12,
            "claim_type": "dependent",
            "change_type": "수정",
            "change_code": "A",
            "text": "청구항 1 내지 3 중 어느 한 항에 있어서, 상기 생물활성 분획은 액체 생물활성 분획이며, 여기서 상기 원상태 성분은 하기를 포함하는, 조성물:\n상기 액체 생물활성 분획의 20,000 ng/ml 미만 수준에서 피브리노겐;\n상기 액체 생물활성 분획의 적어도 2 mg/dL 수준에서 알부민;\n상기 액체 생물활성 분획의 적어도 1 g/dL 수준에서 글로불린;\n상기 액체 생물활성 분획의 적어도 5000 pg/mL 수준에서 TGF-β1;\n상기 액체 생물활성 분획의 적어도 20 pg/mL 수준에서 EGF;\n상기 액체 생물활성 분획의 적어도 5 pg/mL 수준에서 FGF-베타;\n상기 액체 생물활성 분획의 적어도 200 pg/mL 수준에서 PDGF-AA;\n상기 액체 생물활성 분획의 적어도 50 pg/mL 수준에서 PDGF-BB;\n상기 액체 생물활성 분획의 적어도 100 pg/mL 수준에서 SDF-1α; 및\n상기 액체 생물활성 분획의 적어도 10 pg/mL 수준에서 VEGF.",
            "refers_to": [
              1,
              2,
              3
            ]
          },
          {
            "claim_number": 13,
            "claim_type": "dependent",
            "change_type": "수정",
            "change_code": "A",
            "text": "청구항 1 내지 3 중 어느 한 항에 있어서,\n상기 조성물은 260-340 mmol/kg 범위의 오스몰농도를 갖는, 조성물.",
            "refers_to": [
              1,
              2,
              3
            ]
          },
          {
            "claim_number": 14,
            "claim_type": "dependent",
            "change_type": "수정",
            "change_code": "A",
            "text": "청구항 1 내지 3 중 어느 한 항에 있어서, \n상기 조성물은 6.8 내지 7.8 범위의 pH를 갖는, 조성물.",
            "refers_to": [
              1,
              2,
              3
            ]
          },
          {
            "claim_number": 15,
            "claim_type": "dependent",
            "change_type": "수정",
            "change_code": "A",
            "text": "청구항 1 내지 3 중 어느 한 항에 있어서,\n상기 조성물은 상기 혈소판 농축물에 대하여 원상태가 아닌 헤파린은 포함하지 않는, 조성물.",
            "refers_to": [
              1,
              2,
              3
            ]
          },
          {
            "claim_number": 16,
            "claim_type": "dependent",
            "change_type": "수정",
            "change_code": "A",
            "text": "청구항 1 내지 3 중 어느 한 항에 따른 조성물을 포함하는 세포 배양 배지.",
            "refers_to": [
              1,
              2,
              3
            ]
          },
          {
            "claim_number": 18,
            "claim_type": "independent",
            "change_type": "수정",
            "change_code": "A",
            "text": "생물활성 조성물을 제조하는 방법으로서, \n혈소판 및 혈장이 포함된 인간 혈액-유도된 농축물의 혈소판을 용해시켜, 용해된 혈소판 제조물을 만들고;\n상기 용해된 혈소판 제조물 안에 피브리노겐을 피브린으로 전환시킴으로써 용해된 혈소판 제조물로부터 겔 응고를 형성시키고;\n상기 겔 응고로부터 액체를 뽑아내기 위하여 상기 겔 응고를 압착시키고; 및\n상기 겔 응고 고형물로부터 상기 액체를 분리시키는 것을 포함하는, 방법.",
            "refers_to": []
          },
          {
            "claim_number": 19,
            "claim_type": "independent",
            "change_type": "수정",
            "change_code": "A",
            "text": "혈소판 용해물 조성물을 가공하는 방법으로서, \n혈소판 및 혈장이 포함된 인간 혈액-유도된 농축물의 혈소판을 용해시켜, 용해된 혈소판 제조물을 만들고;\n용해된 혈소판 제조물 안에 피브리노겐을 피브린으로 전환시켜 형성된 겔 응고를 압착시켜, 상기 겔 응고로부터 액체를 뽑아내는 것을 포함하는, 방법.",
            "refers_to": []
          },
          {
            "claim_number": 20,
            "claim_type": "dependent",
            "change_type": "수정",
            "change_code": "A",
            "text": "세포를 동결보존하는 방법으로서, \n상기 세포 및 청구항 1 내지 3 중 어느 한 항에 따른 조성물이 포함된 세포 조성물을 냉동보존 조건에 두는 것을 포함하는, 방법.",
            "refers_to": [
              1,
              2,
              3
            ]
          },
          {
            "claim_number": 21,
            "claim_type": "dependent",
            "change_type": "수정",
            "change_code": "A",
            "text": "청구항 1 내지 3 중 어느 한 항에 있어서, 상기 조성물은 액체 전달 장치, 바람직하게는 점안기 안에 보관된, 조성물.",
            "refers_to": [
              1,
              2,
              3
            ]
          },
          {
            "claim_number": 22,
            "claim_type": "dependent",
            "change_type": "수정",
            "change_code": "A",
            "text": "청구항 1 내지 3 중 어느 한 항에 있어서, 상기 조성물은 갯과(canine) 환자에서 질환 또는 병든 상태를 치료하는데 효과적인, 조성물.",
            "refers_to": [
              1,
              2,
              3
            ]
          },
          {
            "claim_number": 23,
            "claim_type": "dependent",
            "change_type": "수정",
            "change_code": "A",
            "text": "청구항 22에 있어서, 상기 병든 상태는 건성각결막염(keratoconjunctivitis sicca)을 포함하는, 조성물.",
            "refers_to": [
              22
            ]
          },
          {
            "claim_number": 24,
            "claim_type": "dependent",
            "change_type": "수정",
            "change_code": "A",
            "text": "청구항 1에 있어서, 상기 생물활성 분획은 액체 생물활성 분획이며, 그리고 여기서 상기 조성물은 하기를 포함하는 조성물:\n약 200 pg/mL 내지 약 350 pg/mL 수준에서 FGF-2;\n약 1800 pg/mL 내지 약 3100 pg/mL 수준에서 EGF; \n약 24,000 pg/mL 내지 약 28,000 pg/mL 수준에서 PDGF-AA; \n약 50 ng/mL 내지 약 80 ng/mL 수준에서 PDGF-BB; \n약 500 pg/mL 내지 약 800 pg/mL 수준에서 VEGF; \n약 60 ng/mL 내지 약 90 ng/mL 수준에서 TGF-b; 그리고\n2.5㎍/mL 미만의 수준에서 피브리노겐.",
            "refers_to": [
              1
            ]
          },
          {
            "claim_number": 25,
            "claim_type": "independent",
            "change_type": "삭제",
            "change_code": "D",
            "text": "",
            "refers_to": []
          },
          {
            "claim_number": 26,
            "claim_type": "independent",
            "change_type": "삭제",
            "change_code": "D",
            "text": "",
            "refers_to": []
          },
          {
            "claim_number": 27,
            "claim_type": "independent",
            "change_type": "삭제",
            "change_code": "D",
            "text": "",
            "refers_to": []
          },
          {
            "claim_number": 28,
            "claim_type": "independent",
            "change_type": "삭제",
            "change_code": "D",
            "text": "",
            "refers_to": []
          },
          {
            "claim_number": 29,
            "claim_type": "independent",
            "change_type": "삭제",
            "change_code": "D",
            "text": "",
            "refers_to": []
          },
          {
            "claim_number": 30,
            "claim_type": "independent",
            "change_type": "삭제",
            "change_code": "D",
            "text": "",
            "refers_to": []
          },
          {
            "claim_number": 31,
            "claim_type": "independent",
            "change_type": "삭제",
            "change_code": "D",
            "text": "",
            "refers_to": []
          },
          {
            "claim_number": 32,
            "claim_type": "independent",
            "change_type": "삭제",
            "change_code": "D",
            "text": "",
            "refers_to": []
          },
          {
            "claim_number": 33,
            "claim_type": "independent",
            "change_type": "삭제",
            "change_code": "D",
            "text": "",
            "refers_to": []
          },
          {
            "claim_number": 34,
            "claim_type": "independent",
            "change_type": "삭제",
            "change_code": "D",
            "text": "",
            "refers_to": []
          },
          {
            "claim_number": 35,
            "claim_type": "independent",
            "change_type": "삭제",
            "change_code": "D",
            "text": "",
            "refers_to": []
          },
          {
            "claim_number": 36,
            "claim_type": "independent",
            "change_type": "삭제",
            "change_code": "D",
            "text": "",
            "refers_to": []
          },
          {
            "claim_number": 37,
            "claim_type": "independent",
            "change_type": "삭제",
            "change_code": "D",
            "text": "",
            "refers_to": []
          },
          {
            "claim_number": 38,
            "claim_type": "independent",
            "change_type": "삭제",
            "change_code": "D",
            "text": "",
            "refers_to": []
          },
          {
            "claim_number": 39,
            "claim_type": "independent",
            "change_type": "삭제",
            "change_code": "D",
            "text": "",
            "refers_to": []
          },
          {
            "claim_number": 40,
            "claim_type": "independent",
            "change_type": "삭제",
            "change_code": "D",
            "text": "",
            "refers_to": []
          },
          {
            "claim_number": 41,
            "claim_type": "independent",
            "change_type": "삭제",
            "change_code": "D",
            "text": "",
            "refers_to": []
          },
          {
            "claim_number": 42,
            "claim_type": "independent",
            "change_type": "삭제",
            "change_code": "D",
            "text": "",
            "refers_to": []
          },
          {
            "claim_number": 43,
            "claim_type": "independent",
            "change_type": "삭제",
            "change_code": "D",
            "text": "",
            "refers_to": []
          },
          {
            "claim_number": 44,
            "claim_type": "independent",
            "change_type": "삭제",
            "change_code": "D",
            "text": "",
            "refers_to": []
          },
          {
            "claim_number": 45,
            "claim_type": "independent",
            "change_type": "삭제",
            "change_code": "D",
            "text": "",
            "refers_to": []
          },
          {
            "claim_number": 46,
            "claim_type": "independent",
            "change_type": "삭제",
            "change_code": "D",
            "text": "",
            "refers_to": []
          },
          {
            "claim_number": 47,
            "claim_type": "independent",
            "change_type": "삭제",
            "change_code": "D",
            "text": "",
            "refers_to": []
          },
          {
            "claim_number": 48,
            "claim_type": "independent",
            "change_type": "삭제",
            "change_code": "D",
            "text": "",
            "refers_to": []
          },
          {
            "claim_number": 49,
            "claim_type": "independent",
            "change_type": "삭제",
            "change_code": "D",
            "text": "",
            "refers_to": []
          },
          {
            "claim_number": 50,
            "claim_type": "independent",
            "change_type": "삭제",
            "change_code": "D",
            "text": "",
            "refers_to": []
          },
          {
            "claim_number": 51,
            "claim_type": "independent",
            "change_type": "삭제",
            "change_code": "D",
            "text": "",
            "refers_to": []
          },
          {
            "claim_number": 52,
            "claim_type": "independent",
            "change_type": "삭제",
            "change_code": "D",
            "text": "",
            "refers_to": []
          },
          {
            "claim_number": 53,
            "claim_type": "independent",
            "change_type": "삭제",
            "change_code": "D",
            "text": "",
            "refers_to": []
          },
          {
            "claim_number": 54,
            "claim_type": "independent",
            "change_type": "삭제",
            "change_code": "D",
            "text": "",
            "refers_to": []
          },
          {
            "claim_number": 55,
            "claim_type": "independent",
            "change_type": "삭제",
            "change_code": "D",
            "text": "",
            "refers_to": []
          },
          {
            "claim_number": 56,
            "claim_type": "independent",
            "change_type": "삭제",
            "change_code": "D",
            "text": "",
            "refers_to": []
          },
          {
            "claim_number": 57,
            "claim_type": "independent",
            "change_type": "삭제",
            "change_code": "D",
            "text": "",
            "refers_to": []
          },
          {
            "claim_number": 58,
            "claim_type": "independent",
            "change_type": "삭제",
            "change_code": "D",
            "text": "",
            "refers_to": []
          },
          {
            "claim_number": 59,
            "claim_type": "independent",
            "change_type": "삭제",
            "change_code": "D",
            "text": "",
            "refers_to": []
          },
          {
            "claim_number": 60,
            "claim_type": "independent",
            "change_type": "삭제",
            "change_code": "D",
            "text": "",
            "refers_to": []
          },
          {
            "claim_number": 61,
            "claim_type": "independent",
            "change_type": "삭제",
            "change_code": "D",
            "text": "",
            "refers_to": []
          },
          {
            "claim_number": 62,
            "claim_type": "independent",
            "change_type": "삭제",
            "change_code": "D",
            "text": "",
            "refers_to": []
          },
          {
            "claim_number": 63,
            "claim_type": "independent",
            "change_type": "삭제",
            "change_code": "D",
            "text": "",
            "refers_to": []
          },
          {
            "claim_number": 64,
            "claim_type": "independent",
            "change_type": "삭제",
            "change_code": "D",
            "text": "",
            "refers_to": []
          },
          {
            "claim_number": 65,
            "claim_type": "independent",
            "change_type": "삭제",
            "change_code": "D",
            "text": "",
            "refers_to": []
          },
          {
            "claim_number": 66,
            "claim_type": "independent",
            "change_type": "삭제",
            "change_code": "D",
            "text": "",
            "refers_to": []
          },
          {
            "claim_number": 67,
            "claim_type": "independent",
            "change_type": "삭제",
            "change_code": "D",
            "text": "",
            "refers_to": []
          },
          {
            "claim_number": 68,
            "claim_type": "independent",
            "change_type": "삭제",
            "change_code": "D",
            "text": "",
            "refers_to": []
          },
          {
            "claim_number": 69,
            "claim_type": "independent",
            "change_type": "삭제",
            "change_code": "D",
            "text": "",
            "refers_to": []
          },
          {
            "claim_number": 70,
            "claim_type": "independent",
            "change_type": "삭제",
            "change_code": "D",
            "text": "",
            "refers_to": []
          },
          {
            "claim_number": 71,
            "claim_type": "independent",
            "change_type": "삭제",
            "change_code": "D",
            "text": "",
            "refers_to": []
          },
          {
            "claim_number": 72,
            "claim_type": "independent",
            "change_type": "삭제",
            "change_code": "D",
            "text": "",
            "refers_to": []
          }
        ]
      },
      {
        "version": 3,
        "receipt_date": "20210119",
        "document_name": "[명세서등 보정]보정서",
        "claim_count": 24,
        "claims": [
          {
            "claim_number": 1,
            "claim_type": "independent",
            "change_type": "수정",
            "change_code": "A",
            "text": "생물활성(bioactive) 조성물의 제조 방법으로서, 상기 방법이:\n혈소판 및 혈장을 포함하는 인간 혈액-유래된 농축물의 혈소판을 용해시켜 용해된 혈소판 제제(preparation)를 형성하는 단계;\n상기 용해된 혈소판 제제에서 피브리노겐을 피브린으로 전환시키는 응고제를 첨가하여 상기 용해된 혈소판 제제로부터 응고 겔(gel clot)을 형성하는 단계;\n상기 응고 겔을 압축(compress)하여 응고 겔로부터 액체를 짜내고(express) 상기 응고 겔의 고체로부터 액체를 분리하는 단계를 포함하고, 상기 압축 단계는 2개 이상의 표면 사이에서 응고 겔을 압박(press)하는 단계를 포함하고;\n상기 생물활성 조성물의 제조 동안 헤파린이 첨가되지 않는, 생물활성 조성물의 제조 방법.",
            "refers_to": []
          },
          {
            "claim_number": 2,
            "claim_type": "dependent",
            "change_type": "수정",
            "change_code": "A",
            "text": "청구항 1에 있어서, 상기 생물활성 조성물을 세포성 현탁 조성물 안에 혼입시키는 단계를 추가로 포함하는, 방법,",
            "refers_to": [
              1
            ]
          },
          {
            "claim_number": 3,
            "claim_type": "dependent",
            "change_type": "수정",
            "change_code": "A",
            "text": "청구항 2에 있어서, 상기 세포성 현탁 조성물을 냉동보존시키는 단계를 추가로 포함하는, 방법.",
            "refers_to": [
              2
            ]
          },
          {
            "claim_number": 4,
            "claim_type": "independent",
            "change_type": "삭제",
            "change_code": "D",
            "text": "",
            "refers_to": []
          },
          {
            "claim_number": 5,
            "claim_type": "independent",
            "change_type": "삭제",
            "change_code": "D",
            "text": "",
            "refers_to": []
          },
          {
            "claim_number": 6,
            "claim_type": "independent",
            "change_type": "삭제",
            "change_code": "D",
            "text": "",
            "refers_to": []
          },
          {
            "claim_number": 7,
            "claim_type": "independent",
            "change_type": "삭제",
            "change_code": "D",
            "text": "",
            "refers_to": []
          },
          {
            "claim_number": 8,
            "claim_type": "independent",
            "change_type": "삭제",
            "change_code": "D",
            "text": "",
            "refers_to": []
          },
          {
            "claim_number": 9,
            "claim_type": "independent",
            "change_type": "삭제",
            "change_code": "D",
            "text": "",
            "refers_to": []
          },
          {
            "claim_number": 10,
            "claim_type": "independent",
            "change_type": "삭제",
            "change_code": "D",
            "text": "",
            "refers_to": []
          },
          {
            "claim_number": 11,
            "claim_type": "independent",
            "change_type": "삭제",
            "change_code": "D",
            "text": "",
            "refers_to": []
          },
          {
            "claim_number": 12,
            "claim_type": "independent",
            "change_type": "삭제",
            "change_code": "D",
            "text": "",
            "refers_to": []
          },
          {
            "claim_number": 13,
            "claim_type": "independent",
            "change_type": "삭제",
            "change_code": "D",
            "text": "",
            "refers_to": []
          },
          {
            "claim_number": 14,
            "claim_type": "independent",
            "change_type": "삭제",
            "change_code": "D",
            "text": "",
            "refers_to": []
          },
          {
            "claim_number": 15,
            "claim_type": "independent",
            "change_type": "삭제",
            "change_code": "D",
            "text": "",
            "refers_to": []
          },
          {
            "claim_number": 16,
            "claim_type": "independent",
            "change_type": "삭제",
            "change_code": "D",
            "text": "",
            "refers_to": []
          },
          {
            "claim_number": 17,
            "claim_type": "independent",
            "change_type": "삭제",
            "change_code": "D",
            "text": "",
            "refers_to": []
          },
          {
            "claim_number": 18,
            "claim_type": "independent",
            "change_type": "삭제",
            "change_code": "D",
            "text": "",
            "refers_to": []
          },
          {
            "claim_number": 19,
            "claim_type": "independent",
            "change_type": "삭제",
            "change_code": "D",
            "text": "",
            "refers_to": []
          },
          {
            "claim_number": 20,
            "claim_type": "independent",
            "change_type": "삭제",
            "change_code": "D",
            "text": "",
            "refers_to": []
          },
          {
            "claim_number": 21,
            "claim_type": "independent",
            "change_type": "삭제",
            "change_code": "D",
            "text": "",
            "refers_to": []
          },
          {
            "claim_number": 22,
            "claim_type": "independent",
            "change_type": "삭제",
            "change_code": "D",
            "text": "",
            "refers_to": []
          },
          {
            "claim_number": 23,
            "claim_type": "independent",
            "change_type": "삭제",
            "change_code": "D",
            "text": "",
            "refers_to": []
          },
          {
            "claim_number": 24,
            "claim_type": "independent",
            "change_type": "삭제",
            "change_code": "D",
            "text": "",
            "refers_to": []
          }
        ]
      },
      {
        "version": 4,
        "receipt_date": "20210625",
        "document_name": "[명세서등 보정]보정서(재심사)",
        "claim_count": 1,
        "claims": [
          {
            "claim_number": 1,
            "claim_type": "independent",
            "change_type": "수정",
            "change_code": "A",
            "text": "생물활성(bioactive) 조성물의 제조 방법으로서, 상기 방법이:\n혈소판 및 혈장을 포함하는 인간 혈액-유래된 농축물의 혈소판을 용해시켜 용해된 혈소판 제제(preparation)를 형성하는 단계;\n상기 용해된 혈소판 제제에서 피브리노겐을 피브린으로 전환시키는 응고제를 첨가하여 상기 용해된 혈소판 제제로부터 응고 겔(gel clot)을 형성하는 단계;\n상기 응고 겔을 압축(compress)하여 응고 겔로부터 액체를 짜내고(express) 상기 응고 겔의 고체로부터 액체를 분리하는 단계를 포함하고, 상기 압축 단계는 2개 이상의 표면 사이에서 응고 겔을 압박(press)하는 단계를 포함하고;\n상기 생물활성 조성물의 제조 동안 헤파린이 첨가되지 않고;\n상기 생물활성 조성물이 20,000 ng/mL 미만의 수준으로 피브리노겐을 포함하는, 생물활성 조성물의 제조 방법.",
            "refers_to": []
          }
        ]
      }
    ],
    "summary": {
      "before_claim_count": 72,
      "after_claim_count": 1,
      "total_versions": 4
    }
  },
  "familyInfoArray": {
    "familyInfo": ""
  },
  "internationalInfoArray": {
    "internationalInfo": {
      "internationOpenDate": "2015.03.05",
      "internationOpenNumber": "WO2015031465",
      "internationalApplicationDate": "2014.08.27",
      "internationalApplicationNumber": "PCT/US2014/052885"
    }
  },
  "applicantInfoArray": {
    "applicantInfo": {
      "address": "미국 인디애나주 ***** 인디애나폴리스 인디애나 애비뉴 ****",
      "code": "520160184859",
      "country": "미국",
      "engName": "COOK GENERAL BIOTECHNOLOGY LLC",
      "name": "쿡 제너럴 바이오테크놀로지 엘엘씨"
    }
  },
  "inventorInfoArray": {
    "inventorInfo": [
      {
        "address": "미국 인디애나주 *****...",
        "code": "",
        "country": "",
        "engName": "WOODS, Erik, John",
        "name": "우즈 에릭 존"
      },
      {
        "address": "미국 인디애나주 ***** ...",
        "code": "",
        "country": "",
        "engName": "TAYLOR, Christopher, Gregory",
        "name": "테일러 크리스토퍼 그레고리"
      }
    ]
  },
  "agentInfoArray": {
    "agentInfo": {
      "address": "서울특별시 종로구 세종대로 ***, **층 (세종로, 광화문빌딩)(법무법인센트럴)",
      "code": "919990006014",
      "country": "대한민국",
      "engName": "HOON CHANG",
      "name": "장훈"
    }
  },
  "priorityInfoArray": {
    "priorityInfo": {
      "priorityApplicationCountry": "미국",
      "priorityApplicationDate": "2013.08.27",
      "priorityApplicationNumber": "61/870,686"
    }
  },
  "designatedStateInfoArray": "",
  "priorArtDocumentsInfoArray": {
    "priorArtDocumentsInfo": [
      {
        "documentsNumber": "WO2013003356 A1",
        "examinerQuotationFlag": "Y"
      },
      {
        "documentsNumber": "WO2009087560 A1",
        "examinerQuotationFlag": ""
      },
      {
        "documentsNumber": "WO2010007502 A2",
        "examinerQuotationFlag": ""
      },
      {
        "documentsNumber": "BIOMATERIALS, Vol. 34, No. 32, pp. 7840-7850 (2013)",
        "examinerQuotationFlag": ""
      }
    ]
  },
  "legalStatusInfoArray": {
    "legalStatusInfo": [
      {
        "commonCodeName": "수리 (Accepted)",
        "documentEngName": "[Patent Application] Document according to the Article 203 of Patent Act",
        "documentName": "[특허출원]특허법 제203조에 따른 서면",
        "receiptDate": "2016.03.21",
        "receiptNumber": "1-1-2016-0269925-48"
      },
      {
        "commonCodeName": "발송처리완료 (Completion of Transmission)",
        "documentEngName": "Request for Amendment",
        "documentName": "보정요구서",
        "receiptDate": "2016.04.04",
        "receiptNumber": "1-5-2016-0049711-74"
      },
      {
        "commonCodeName": "수리 (Accepted)",
        "documentEngName": "[Amendment to Patent Application, etc.] Amendment",
        "documentName": "[출원서등 보정]보정서",
        "receiptDate": "2016.04.11",
        "receiptNumber": "1-1-2016-0347227-06"
      },
      {
        "commonCodeName": "발송처리완료 (Completion of Transmission)",
        "documentEngName": "Notice of Acceptance",
        "documentName": "수리안내서",
        "receiptDate": "2016.04.18",
        "receiptNumber": "1-5-2016-0056639-48"
      },
      {
        "commonCodeName": "보정승인간주 (Regarded as an acceptance of amendment)",
        "documentEngName": "[Amendment to Description, etc.] Amendment",
        "documentName": "[명세서등 보정]보정서",
        "receiptDate": "2019.08.26",
        "receiptNumber": "1-1-2019-0876315-93"
      },
      {
        "commonCodeName": "수리 (Accepted)",
        "documentEngName": "[Request for Examination] Request for Examination (Request for Preferential Examination)",
        "documentName": "[심사청구]심사청구(우선심사신청)서",
        "receiptDate": "2019.08.26",
        "receiptNumber": "1-1-2019-0876333-15"
      },
      {
        "commonCodeName": "발송처리완료 (Completion of Transmission)",
        "documentEngName": "Notification of reason for refusal",
        "documentName": "의견제출통지서",
        "receiptDate": "2020.11.19",
        "receiptNumber": "9-5-2020-0805417-69"
      },
      {
        "commonCodeName": "수리 (Accepted)",
        "documentEngName": "",
        "documentName": "[거절이유 등 통지에 따른 의견]의견서·답변서·소명서",
        "receiptDate": "2021.01.19",
        "receiptNumber": "1-1-2021-0071566-80"
      },
      {
        "commonCodeName": "보정승인간주 (Regarded as an acceptance of amendment)",
        "documentEngName": "[Amendment to Description, etc.] Amendment",
        "documentName": "[명세서등 보정]보정서",
        "receiptDate": "2021.01.19",
        "receiptNumber": "1-1-2021-0071532-38"
      },
      {
        "commonCodeName": "발송처리완료 (Completion of Transmission)",
        "documentEngName": "Decision to Refuse a Patent",
        "documentName": "거절결정서",
        "receiptDate": "2021.05.27",
        "receiptNumber": "9-5-2021-0423922-90"
      },
      {
        "commonCodeName": "보정승인 (Acceptance of amendment)",
        "documentEngName": "Amendment to Description, etc(Reexamination)",
        "documentName": "[명세서등 보정]보정서(재심사)",
        "receiptDate": "2021.06.25",
        "receiptNumber": "1-1-2021-0734830-57"
      },
      {
        "commonCodeName": "수리 (Accepted)",
        "documentEngName": "",
        "documentName": "[거절이유 등 통지에 따른 의견]의견서·답변서·소명서",
        "receiptDate": "2021.06.25",
        "receiptNumber": "1-1-2021-0734858-24"
      },
      {
        "commonCodeName": "발송처리완료 (Completion of Transmission)",
        "documentEngName": "Decision to Grant Registration",
        "documentName": "등록결정서",
        "receiptDate": "2021.07.08",
        "receiptNumber": "9-5-2021-0542984-12"
      }
    ]
  },
  "imagePathInfo": {
    "docName": "1020167007410.jpg",
    "largePath": "http://plus.kipris.or.kr/openapi/fileToss.jsp?arg=6c650beb4cee9ce4122b704b88878c93f5f0cac31a0f4d8ad5b5f3b0681843cc4dfa8d00e3ed1d7ec5e680967a70d431fa343c6ed13680180fb04c7b0906b1edb29c4332ae71ade0",
    "path": "http://plus.kipris.or.kr/openapi/fileToss.jsp?arg=ed43a0609e94d6e22d01c5c32ba711cfdc0f8f849e17b0eb1f893e5f881aff563c577ca0b7fc77b14b1ea428e219e5ae441fa3723beb07072df14baffcfa2ed632ba6a3d958e0b3b"
  },
  "rndInfoArray": ""
}